Workbook
Name CIQWBGuid: "2cd8126d-26c3-430c-b7fa-a069e3a1fc62"
Name IQ_CH: 110000
Name IQ_CQ: 5000
Name IQ_CY: 10000
Name IQ_DAILY: 500000
Name IQ_DNTM: 700000
Name IQ_FH: 100000
Name IQ_FQ: 500
Name IQ_FWD_CY: 10001
Name IQ_FWD_CY1: 10002
Name IQ_FWD_CY2: 10003
Name IQ_FWD_FY: 1001
Name IQ_FWD_FY1: 1002
Name IQ_FWD_FY2: 1003
Name IQ_FWD_Q: 501
Name IQ_FWD_Q1: 502
Name IQ_FWD_Q2: 503
Name IQ_FY: 1000
Name IQ_LATESTK: 1000
Name IQ_LATESTQ: 500
Name IQ_LTM: 2000
Name IQ_LTMMONTH: 120000
Name IQ_MONTH: 15000
Name IQ_MTD: 800000
Name IQ_NAMES_REVISION_DATE_: 43412.7003240741
Name IQ_NTM: 6000
Name IQ_QTD: 750000
Name IQ_TODAY: 0
Name IQ_WEEK: 50000
Name IQ_YTD: 3000
Name IQ_YTDMONTH: 130000

Sheet M&A Assumptions & Analysis
A1: ="Merger Assumptions for "&D6&" & "&D7 -> Merger Assumptions for Online Company Inc & Brick 'n' Mortar Co
A3: Assumptions
A5: Transaction Inputs | F5: Scenarios
A6: Acquirer Name | D6: Online Company Inc | F6: Scenario # | G6: LIVE --> | H6: 1 | I6: 1 | J6: =+I6+1 -> 2 | K6: =+J6+1 -> 3 | L6: =+K6+1 -> 4 | M6: =+L6+1 -> 5
A7: Target Name | D7: Brick 'n' Mortar Co
A8: Acquirer Share Price | D8: 11.75 | F8: Synergies
A9: Target Share Price | D9: 17.3 | F9: Revenue enhancement | H9: 5500 | I9: 6000 | J9: 6000 | K9: 6500 | L9: 6500
A10: Transaction Close Date | D10: 45838 | F10: COGS savings | H10: 875 | I10: 875 | J10: 875 | K10: 875 | L10: 875
A11: Financial Reporting Units | D11: $'000s | F11: Marketing savings | H11: 1250 | I11: 1250 | J11: 1250 | K11: 1250 | L11: 1250
A12: Currency | D12: USD | F12: General & Admin savings | H12: 1000 | I12: 1000 | J12: 1000 | K12: 1000 | L12: 1000
A14: Restructuring Charges | D14: 2000 | F14: Synergies in Year 1 (full yr.) | H14: 0.3 | I14: 0.3 | J14: 0.3 | K14: 0.3 | L14: 0.3
A15: Equity Issuance Fees | D15: 0.03 | F15: Synergies in Year 2 | H15: 0.65 | I15: 0.65 | J15: 0.65 | K15: 0.65 | L15: 0.65
A16: Debt Issuance Fees | D16: 0.03 | F16: Synergies in Years 3+ | H16: 1 | I16: 1 | J16: 1 | K16: 1 | L16: 1
A17: Other Closing Costs | D17: 2000
F18: Financing
A19: Replace Target Debt | D19: Yes | F19: Debt Tranche
A20: Replace Acquirer Debt | D20: No | F20: Senior Debt A | H20: 0 | I20: 100000 | J20: 100000 | K20: 100000 | L20: 100000
F21: Senior Debt B | H21: 0 | I21: 0 | J21: 50000 | K21: 50000 | L21: 50000
A22: Acquirer FD Shares Outstanding | D22: 50000 | F22: Subordinated Debt | H22: 0 | I22: 0 | J22: 0 | K22: 25000 | L22: 25000
A23: Target FD Share Outstanding | D23: 25000 | F23: Interest Rate
A24: Shares Issued | D24: =D39*D37 -> 46000 | F24: Senior Debt A | H24: 0.055 | I24: 0.055 | J24: 0.055 | K24: 0.055 | L24: 0.055
A25: Pro Forma Shares Outstanding | D25: =D22+D24 -> 96000 | F25: Senior Debt B | H25: 0.0575 | I25: 0.0575 | J25: 0.0575 | K25: 0.0575 | L25: 0.0575
F26: Subordinated Debt | H26: 0.0825 | I26: 0.0825 | J26: 0.0825 | K26: 0.0825 | L26: 0.0825
A27: Share Issuance Discount | D27: 0.01
A28: Share Issuance Price | D28: =D8*(1-D27) -> 11.6325
F29: Transaction
F30: Takeover Premium | H30: 0.15 | I30: 0.15 | J30: 0.2 | K30: 0.25 | L30: 0.3
A31: Purchase Price | F31: Cash Consideration | H31: 0 | I31: 0.2 | J31: 0.4 | K31: 0.5 | L31: 0.55
A32: Target Share Price | D32: =+D9 -> 17.3
A33: Takeover Premium | D33: =+H30 -> 0.15
A34: Offer Price | D34: =D32*(1+D33) -> 19.895
F35: Sources & Uses of Cash
A36: Acquirer Share Price | D36: =+D8 -> 11.75 | F36: Sources of Cash
A37: Share Exchange Ratio | D37: 1.84 | F37: Cash | I37: =M44-SUM(I38:I43) -> 7125.28 | K37: Cash Consideration | M37: =+D41*H31 -> 0
F38: Stock Issued | I38: =+M38 -> 497375 | K38: Stock Consideration | M38: =D41-M37 -> 497375
A39: Target Shares Outstanding | D39: =+D23 -> 25000 | F39: Debt Issued | I39: 16801 | K39: Target Debt - Replace (ST+LT) | M39: =+IF(D19="Yes", D42,0) -> 6801
A40: Offer Price | D40: =+D34 -> 19.895 | K40: Acquirer Debt - Replace (ST+LT) | M40: -
A41: Purchase Price | D41: =D39*D40 -> 497375 | K41: Debt Financing Fees | M41: =D16*SUM(M39:M40) -> 204.03
A42: Target Debt (Total Debt ST + LT) | D42: 6801 | K42: Equity Financing Fees | M42: =D15*M38 -> 14921.25
A43: Target Cash | D43: =+'Target Model'!O81 -> 254785.32 | K43: Other Closing Costs | M43: =+D17 -> 2000
A44: Enterprise Value | D44: =+D41+D42-D43 -> 249390.68 | F44: Total Sources | I44: =SUM(I37:I43) -> 521301.28 | K44: Total Uses | M44: =SUM(M37:M43) -> 521301.28
I45: ^ Total cash needed for transaction | M45: ^ Total cash needed for transaction
A48: Goodwill and Purchase Price Allocation
A49: Fair Market Value | D49: Book Value | E49: Fair Value | F49: Adjustment | I49: Purchase Price Allocation
A50: Inventory & Other Current Assets | D50: 168354 | F50: =E50-D50 -> -168354 | I50: Total Purchase Price | M50: =D41 -> 497375
A51: Target PP&E | D51: 95854 | F51: =E51-D51 -> -95854 | I51: Net Book Value of Assets | M51: =308461-14929 -> 293532
A52: Identifiable Intangibles | I52: Excess Purchase Price | M52: =M50-M51 -> 203843
A53: Net Identifiable Assets | D53: =+SUM(D50:D52) -> 264208 | E53: =+SUM(E50:E52) -> 0 | F53: =SUM(F50:F52) -> -264208 | I53: Write-off Existing Goodwill | M53: 0
I54: Fair Value Adjustments | M54: =F53 -> -264208
I55: Excess Purchase Price After Adjustments | M55: =M52-M54 -> 468051
I56: Goodwill | M56: =+M55 -> 468051 | N56: >> Good will on proforma balance sheet
A59: Closing Balance Sheet
A61: Pro Forma Consolidated Balance Sheet
A62: Step # | D62: 1 | E62: =D62+1 -> 2 | F62: =E62+1 -> 3 | G62: =F62+1 -> 4 | H62: =G62+1 -> 5 | I62: =H62+1 -> 6 | J62: =I62+1 -> 7 | K62: =J62+1 -> 8 | L62: =K62+1 -> 9 | M62: =L62+1 -> 10
D63: Acquirer | E63: Target | F63: Fair Value | G63: Target PF | H63: Purchase | I63: Financing | J63: Financing | K63: Financing | L63: Total Adj. | M63: Consol
D64: =+'Acquirer Model'!O4 -> 45838 | E64: =+'Target Model'!O4 -> 45838 | H64: Transaction | I64: Debt + Equity | J64: Fees | K64: Refi Debt | M64: =+D10 -> 45838
A65: Assets
A66: Cash | D66: ='Acquirer Model'!O81 -> 367525.83 | E66: =+'Target Model'!O81 -> 254785.32 | G66: =+SUM(E66:F66) -> 254785.32 | H66: =-M37 -> 0 | I66: =+I39 -> 16801 | J66: =-SUM(M41:M43) -> -17125.28 | K66: =-SUM(M39:M40) -> -6801 | L66: =+SUM(G66:K66) -> 247660.04 | M66: =+L66+D66 -> 615185.86
A67: Accounts Receivable | D67: =+'Acquirer Model'!O82 -> 13712.136 | E67: =+'Target Model'!O82 -> 10916.921 | G67: =+SUM(E67:F67) -> 10916.921 | L67: =+SUM(G67:K67) -> 10916.921 | M67: =+L67+D67 -> 24629.057
A68: Inventory | D68: =+'Acquirer Model'!O83 -> 25595.987 | E68: =+'Target Model'!O83 -> 15631.047 | F68: =+F50 -> -168354 | G68: =SUM(E68:F68) -> -152722.95 | L68: =SUM(G68:K68) -> -152722.95 | M68: =L68+D68 -> -127126.97
A69: Current Assets | D69: =SUM(D66:D68) -> 406833.95 | E69: =SUM(E66:E68) -> 281333.28 | L69: =SUM(L66:L68) -> 105854 | M69: =SUM(M66:M68) -> 512687.95
A70: Property & Equipment | D70: =+'Acquirer Model'!O85 -> 67140 | E70: =+'Target Model'!O85 -> 27127.6 | F70: =+F51 -> -95854 | G70: =SUM(E70:F70) -> -68726.4 | L70: =SUM(G70:K70) -> -68726.4 | M70: =L70+D70 -> -1586.4
A71: Goodwill | D71: =+'Acquirer Model'!O86 -> 0 | E71: =+'Target Model'!O86 -> 0 | G71: =+SUM(E71:F71) -> 0 | H71: =M56 -> 468051 | L71: =SUM(G71:K71) -> 468051 | M71: =L71+D71 -> 468051
A72: Total Assets | D72: =SUM(D69:D71) -> 473973.95 | E72: =SUM(E69:E71) -> 308460.88 | L72: =SUM(L69:L71) -> 505178.6 | M72: =SUM(M69:M71) -> 979152.55
A74: Liabilities
A75: Short Term Debt | D75: =+'Acquirer Model'!O90 -> 0
A76: Accounts Payable | D76: =+'Acquirer Model'!O91 -> 11838.144 | E76: =+'Target Model'!O91 -> 8128.1442 | G76: =SUM(E76:F76) -> 8128.1442 | L76: =SUM(G76:K76) -> 8128.1442 | M76: =D76+L76 -> 19966.288
A77: Current Liabilities | D77: =SUM(D75:D76) -> 11838.144 | E77: =SUM(E75:E76) -> 8128.1442 | L77: =SUM(L75:L76) -> 8128.1442 | M77: =SUM(M75:M76) -> 19966.288
A78: Long Term Debt | D78: =+'Acquirer Model'!O93 -> 10000 | E78: =+'Target Model'!O93 -> 6801 | G78: =+SUM(E78:F78) -> 6801 | I78: =+I39 -> 16801 | K78: =+K66 -> -6801 | L78: =SUM(G78:K78) -> 16801 | M78: =D78+L78 -> 26801
A79: Total Liabilities | D79: =+D78+D77 -> 21838.144 | E79: =+E78+E77 -> 14929.144 | L79: =SUM(L77:L78) -> 24929.144 | M79: =SUM(M77:M78) -> 46767.288
A80: Shareholder's Equity
A81: Equity Capital | D81: =+'Acquirer Model'!O96 -> 70000 | E81: =+'Target Model'!O96 -> 39202.509 | G81: =+SUM(E81:F81) -> 39202.509 | H81: =-G81 -> -39202.509 | I81: =+I38 -> 497375 | L81: =SUM(G81:K81) -> 497375 | M81: =+L81+D81 -> 567375
A82: Retained Earnings | D82: =+'Acquirer Model'!O97 -> 382136.31 | E82: =+'Target Model'!O97 -> 254329.32 | G82: =+SUM(E82:F82) -> 254329.32 | H82: =-G82 -> -254329.32 | J82: =+J66 -> -17125.28 | L82: =SUM(G82:K82) -> -17125.28 | M82: =+L82+D82 -> 365011.03
A83: Shareholder's Equity | D83: =SUM(D81:D82) -> 452136.31 | E83: =SUM(E81:E82) -> 293531.83 | L83: =SUM(L81:L82) -> 480249.72 | M83: =SUM(M81:M82) -> 932386.03
A84: Total Liabilities & Shareholder's Equity | D84: =D79+D83 -> 473974.45 | E84: =E79+E83 -> 308460.97 | F84: =F79+F83 -> 0 | G84: =G79+G83 -> 0 | H84: =H79+H83 -> 0 | I84: =I79+I83 -> 0 | J84: =J79+J83 -> 0 | K84: =K79+K83 -> 0 | ... M84: =M79+M83 -> 979153.32
A86: Check | D86: =D84-D72 -> 0.50524028 | E86: =E84-E72 -> 0.088143695 | L86: =L84-L72 -> 0.25947789 | M86: =M84-M72 -> 0.76471817
A89: Accretion/Dilution Analysis
I91: =+'Pro Forma Model'!J2 -> 2026 | J91: =+'Pro Forma Model'!K2 -> 2027 | K91: =+'Pro Forma Model'!L2 -> 2028 | L91: =+'Pro Forma Model'!M2 -> 2029 | M91: =+'Pro Forma Model'!N2 -> 2030
A93: Earnings Per Share
A94: Acquirer Net Earnings | I94: 33098.602 | J94: 37484.311 | K94: 40290.104 | L94: 42824.293 | M94: 46787.531
A95: Target Net Earnings | I95: 35161.435 | J95: 41926.662 | K95: 47231.641 | L95: 51915.868 | M95: 56511.676
A96: Pro Forma Net Earnings | I96: 65931.96 | J96: 74297.927 | K96: 83175.031 | L96: 89018.395 | M96: 93395.349
A98: Acquirer Shares O/S | I98: =+$D$22 -> 50000 | J98: =+$D$22 -> 50000 | K98: =+$D$22 -> 50000 | L98: =+$D$22 -> 50000 | M98: =+$D$22 -> 50000
A99: Target Share O/S | I99: =+$D$23 -> 25000 | J99: =+$D$23 -> 25000 | K99: =+$D$23 -> 25000 | L99: =+$D$23 -> 25000 | M99: =+$D$23 -> 25000
A100: Pro Forma Shares O/S | I100: =+$D$25 -> 96000 | J100: =+$D$25 -> 96000 | K100: =+$D$25 -> 96000 | L100: =+$D$25 -> 96000 | M100: =+$D$25 -> 96000
A102: Acquirer EPS | I102: =I94/I98 -> 0.66197203 | J102: =J94/J98 -> 0.74968622 | K102: =K94/K98 -> 0.80580209 | L102: =L94/L98 -> 0.85648585 | M102: =M94/M98 -> 0.93575063
A103: Target EPS | I103: =I95/I99 -> 1.4064574 | J103: =J95/J99 -> 1.6770665 | K103: =K95/K99 -> 1.8892656 | L103: =L95/L99 -> 2.0766347 | M103: =M95/M99 -> 2.260467
A104: Pro Forma EPS | I104: =I96/I100 -> 0.68679125 | J104: =J96/J100 -> 0.77393674 | K104: =K96/K100 -> 0.86640657 | L104: =L96/L100 -> 0.92727495 | M104: =M96/M100 -> 0.97286822
A106: Accretion/Dilution | I106: =I104-I102/I102 -> -0.31320875 | J106: =J104-J102/J102 -> -0.22606326 | K106: =K104-K102/K102 -> -0.13359343 | L106: =L104-L102/L102 -> -0.072725049 | M106: =M104-M102/M102 -> -0.027131782
A108: Cash Flow Per Share
A109: Acquirer Cash Flow | I109: 38099.459 | J109: 42937.72 | K109: 48812.388 | L109: 52124.121 | M109: 57202.843
A110: Target Cash Flow | I110: 28274.493 | J110: 32190.447 | K110: 35998.425 | L110: 39408.641 | M110: 42879.544
A111: Pro Forma Cash Flow | I111: 64363.268 | J111: 74655.343 | K111: 89002.18 | L111: 96835.351 | M111: 103369.33
A113: Acquirer Shares O/S | I113: =+$D$22 -> 50000 | J113: =+$D$22 -> 50000 | K113: =+$D$22 -> 50000 | L113: =+$D$22 -> 50000 | M113: =+$D$22 -> 50000
A114: Target Share O/S | I114: =+$D$23 -> 25000 | J114: =+$D$23 -> 25000 | K114: =+$D$23 -> 25000 | L114: =+$D$23 -> 25000 | M114: =+$D$23 -> 25000
A115: Pro Forma Shares O/S | I115: =+$D$25 -> 96000 | J115: =+$D$25 -> 96000 | K115: =+$D$25 -> 96000 | L115: =+$D$25 -> 96000 | M115: =+$D$25 -> 96000
A117: Acquirer CFPS | I117: =I109/I113 -> 0.76198919 | J117: =J109/J113 -> 0.85875441 | K117: =K109/K113 -> 0.97624776 | L117: =L109/L113 -> 1.0424824 | M117: =M109/M113 -> 1.1440569
A118: Target CFPS | I118: =I110/I114 -> 1.1309797 | J118: =J110/J114 -> 1.2876179 | K118: =K110/K114 -> 1.439937 | L118: =L110/L114 -> 1.5763456 | M118: =M110/M114 -> 1.7151817
A119: Pro Forma CFPS | I119: =I111/I115 -> 0.67045071 | J119: =J111/J115 -> 0.77765982 | K119: =K111/K115 -> 0.92710604 | L119: =L111/L115 -> 1.0087016 | M119: =M111/M115 -> 1.0767639
A121: Accretion/Dilution | I121: =I119/I117-I117 -> 0.11787987 | J121: =J119/J117-J117 -> 0.046812789 | K121: =K119/K117-K117 -> -0.02658511 | L121: =L119/L117-L117 -> -0.074886657 | M121: =M119/M117-M117 -> -0.20287644
...

Sheet Pro Forma Model
I1: Forecast Period
A2: Pro Forma Model | H2: CLOSE | I2: ='Acquirer Model'!I2 -> 2025 | J2: ='Acquirer Model'!J2 -> 2026 | K2: ='Acquirer Model'!K2 -> 2027 | L2: ='Acquirer Model'!L2 -> 2028 | M2: ='Acquirer Model'!M2 -> 2029 | N2: ='Acquirer Model'!N2 -> 2030
A3: Balance Sheet Check | H3: =IFERROR(IF(ABS(H71)>1,"ERROR","ok"),"ok") -> ok | I3: =IFERROR(IF(ABS(I71)>1,"ERROR","ok"),"ok") -> ERROR | J3: =IFERROR(IF(ABS(J71)>1,"ERROR","ok"),"ok") -> ERROR | K3: =IFERROR(IF(ABS(K71)>1,"ERROR","ok"),"ok") -> ERROR | L3: =IFERROR(IF(ABS(L71)>1,"ERROR","ok"),"ok") -> ERROR | M3: =IFERROR(IF(ABS(M71)>1,"ERROR","ok"),"ok") -> ERROR | N3: =IFERROR(IF(ABS(N71)>1,"ERROR","ok"),"ok") -> ERROR
A4: End of Period | H4: 45838 | I4: 46022 | J4: 46387 | K4: 46752 | L4: 47118 | M4: 47483 | N4: 47848
A5: Days in Period | H5: 365 | I5: 365 | J5: 365 | K5: 365 | L5: 365 | M5: 365 | N5: 365
A6: Fraction of Year | H6: 1 | I6: 1 | J6: 1 | K6: 1 | L6: 1 | M6: 1 | N6: 1
A8: Assumptions
A11: Debt Amortization Schedule | G11: Check
A12: Senior Debt A | G12: =SUM(H12:N12) -> 1 | H12: 0 | I12: 0.25 | J12: 0.25 | K12: 0.25 | L12: 0.25 | M12: 0 | N12: 0
A13: Senior Debt B | G13: =SUM(H13:N13) -> 1 | H13: 0 | I13: 0 | J13: 0.2 | K13: 0.2 | L13: 0.2 | M13: 0.2 | N13: 0.2
A14: Subordinated Debt | G14: =SUM(H14:N14) -> 1 | H14: 0 | I14: 0 | J14: 0 | K14: 0 | L14: 0 | M14: 0 | N14: 1
A17: Revenue Growth (% Change)
A18: Cost of Goods Sold (% of Revenue)
A19: Marketing, Advertising & Promotion (% of Revenue)
A21: Depreciation & Amortization (% of PP&E) | I21: 0.2 | J21: 0.2 | K21: 0.2 | L21: 0.2 | M21: 0.2 | N21: 0.2
A22: Tax Rate (% of Earnings Before Tax) | I22: 0.3 | J22: 0.3 | K22: 0.3 | L22: 0.3 | M22: 0.3 | N22: 0.3
A23: Accounts Receivable (Days) | I23: 18 | J23: 18 | K23: 18 | L23: 18 | M23: 18 | N23: 18
A24: Inventory (Days) | I24: 80 | J24: 90 | K24: 100 | L24: 100 | M24: 100 | N24: 100
A25: Accounts Payable (Days) | I25: 37 | J25: 37 | K25: 37 | L25: 37 | M25: 37 | N25: 37
A27: Equity Issued (Repaid) ($000's) | I27: 0 | J27: 0 | K27: 0 | L27: 0 | M27: 0 | N27: 0
A28: Dividends Paid | I28: 0 | J28: 0 | K28: 0 | L28: 500 | M28: 500 | N28: 500
A31: Income Statement
A33: Revenue | I33: =+I209 -> 262952.58 | J33: =+J209 -> 295753.01 | K33: =+K209 -> 329321.69 | L33: =+L209 -> 361814.58 | M33: =+M209 -> 390319.75 | N33: =+N209 -> 415771.31
A34: Cost of Goods Sold (COGS) | I34: =+I215 -> 110440.08 | J34: =+J215 -> 123968.42 | K34: =+K215 -> 137757.03 | L34: =+L215 -> 152587.76 | M34: =+M215 -> 167227.16 | N34: =+N215 -> 178399.98
A35: Gross Profit | I35: =+I33-I34 -> 152512.5 | J35: =+J33-J34 -> 171784.59 | K35: =+K33-K34 -> 191564.66 | L35: =+L33-L34 -> 209226.82 | M35: =+M33-M34 -> 223092.59 | N35: =+N33-N34 -> 237371.33
A36: Expenses
A37: Marketing, Advertising & Promotion | I37: 43730.905 | J37: 48505.823 | K37: 53313.746 | L37: 57947.718 | M37: 62683.536 | N37: 66921.152
A38: General & Administrative | I38: =+I227 -> 22000 | J38: =+J227 -> 21700 | K38: =+K227 -> 21350 | L38: =+L227 -> 21000 | M38: =+M227 -> 21000 | N38: =+N227 -> 21000
A39: Depreciation & Amortization | I39: -317.28 | J39: 3896.176 | K39: 7266.9408 | L39: 9963.5526 | M39: 12120.842 | N39: 13846.674
A40: Interest | I40: 2919.08 | J40: 3494.08 | K40: 3494.08 | L40: 1494.08 | M40: 119.08 | N40: 2181.58
A41: Total Expenses | I41: =SUM(I37:I40) -> 68332.705 | J41: =SUM(J37:J40) -> 77596.079 | K41: =SUM(K37:K40) -> 85424.766 | L41: =SUM(L37:L40) -> 90405.351 | M41: =SUM(M37:M40) -> 95923.458 | N41: =SUM(N37:N40) -> 103949.41
A42: Earnings Before Tax | I42: =+I35-I41 -> 84179.793 | J42: =+J35-J41 -> 94188.515 | K42: =+K35-K41 -> 106139.9 | L42: =+L35-L41 -> 118821.47 | M42: =+M35-M41 -> 127169.14 | N42: =+N35-N41 -> 133421.93
A44: Taxes | I44: =I42*0.3 -> 25253.938 | J44: =J42*0.3 -> 28256.554 | K44: =K42*0.3 -> 31841.969 | L44: =L42*0.3 -> 35646.442 | M44: =M42*0.3 -> 38150.741 | N44: =N42*0.3 -> 40026.578
A45: Net Earnings | I45: =I42-I44 -> 58925.855 | J45: =J42-J44 -> 65931.96 | K45: =K42-K44 -> 74297.927 | L45: =L42-L44 -> 83175.031 | M45: =M42-M44 -> 89018.395 | N45: =N42-N44 -> 93395.349
A48: Balance Sheet
A50: Assets
A51: Cash | H51: 615185.86 | I51: 506520.51 | J51: 550133.78 | K51: 584039.12 | L51: 651791.3 | M51: 727376.65 | N51: 799495.99
A52: Accounts Receivable | H52: 24629.057 | I52: =I33*I23/365 -> 12967.525 | J52: =J33*J23/365 -> 14585.08 | K52: =K33*K23/365 -> 16240.522 | L52: =L33*L23/365 -> 17842.911 | M52: =M33*M23/365 -> 19248.645 | N52: =N33*N23/365 -> 20503.791
A53: Inventory | H53: -127126.97 | I53: =I34*I24/365 -> 24206.046 | J53: =J34*J24/365 -> 30567.555 | K53: =K34*K24/365 -> 37741.651 | L53: =L34*L24/365 -> 41804.865 | M53: =M34*M24/365 -> 45815.659 | N53: =N34*N24/365 -> 48876.706
A54: Current Assets | H54: =SUM(H51:H53) -> 512687.95 | I54: =SUM(I51:I53) -> 543694.08 | J54: =SUM(J51:J53) -> 595286.41 | K54: =SUM(K51:K53) -> 638021.29 | L54: =SUM(L51:L53) -> 711439.08 | M54: =SUM(M51:M53) -> 792440.96 | N54: =SUM(N51:N53) -> 868876.48
A55: Property & Equipment | H55: -1586.4 | I55: 19480.88 | J55: 36334.704 | K55: 49817.763 | L55: 60604.211 | M55: 69233.368 | N55: 76136.695
A56: Goodwill | H56: 468051.26 | I56: 468051 | J56: 468051 | K56: 468051 | L56: 468051 | M56: 468051 | N56: 468051
A57: Total Assets | H57: 979152.81 | I57: =SUM(I54:I56) -> 1031226 | J57: =SUM(J54:J56) -> 1099672.1 | K57: =SUM(K54:K56) -> 1155890.1 | L57: =SUM(L54:L56) -> 1240094.3 | M57: =SUM(M54:M56) -> 1329725.3 | N57: =SUM(N54:N56) -> 1413064.2
A59: Liabilities
A60: Short Term Debt
A61: Accounts Payable | H61: 19966.288 | I61: =I34*I25/365 -> 11195.296 | J61: =J34*J25/365 -> 12566.661 | K61: =K34*K25/365 -> 13964.411 | L61: =L34*L25/365 -> 15467.8 | M61: =M34*M25/365 -> 16951.794 | N61: =N34*N25/365 -> 18084.381
A62: Current Liabilities | H62: 19966.288 | I62: =SUM(I60:I61) -> 11195.296 | J62: =SUM(J60:J61) -> 12566.661 | K62: =SUM(K60:K61) -> 13964.411 | L62: =SUM(L60:L61) -> 15467.8 | M62: =SUM(M60:M61) -> 16951.794 | N62: =SUM(N60:N61) -> 18084.381
A63: Long Term Debt | H63: 26801 | I63: 16801 | J63: 16801 | K63: -3199 | L63: -3199 | M63: -3199 | N63: -13199
A64: Total Liabilities | H64: 46767.288 | I64: =+I62+I63 -> 27996.296 | J64: =+J62+J63 -> 29367.661 | K64: =+K62+K63 -> 10765.411 | L64: =+L62+L63 -> 12268.8 | M64: =+M62+M63 -> 13752.794 | N64: =+N62+N63 -> 4885.3813
A65: Shareholder's Equity
A66: Equity Capital | H66: 567375 | I66: =+H66+I27 -> 567375 | J66: =+I66+J27 -> 567375 | K66: =+J66+K27 -> 567375 | L66: =+K66+L27 -> 567375 | M66: =+L66+M27 -> 567375 | N66: =+M66+N27 -> 567375
A67: Retained Earnings | H67: 365011.03 | I67: =H67+I45-I28 -> 423936.88 | J67: =I67+J45-J28 -> 489868.84 | K67: =J67+K45-K28 -> 564166.77 | L67: =K67+L45-L28 -> 646841.8 | M67: =L67+M45-M28 -> 735360.2 | N67: =M67+N45-N28 -> 828255.55
A68: Shareholder's Equity | H68: 932386.03 | I68: =SUM(I66:I67) -> 991311.88 | J68: =SUM(J66:J67) -> 1057243.8 | K68: =SUM(K66:K67) -> 1131541.8 | L68: =SUM(L66:L67) -> 1214216.8 | M68: =SUM(M66:M67) -> 1302735.2 | N68: =SUM(N66:N67) -> 1395630.5
A69: Total Liabilities & Shareholder's Equity | H69: 979153.32 | I69: =I68+I64 -> 1019308.2 | J69: =J64+J68 -> 1086611.5 | K69: =K64+K68 -> 1142307.2 | L69: =L64+L68 -> 1226485.6 | M69: =M64+M68 -> 1316488 | N69: =N64+N68 -> 1400515.9
A71: Check | H71: =H69-H57 -> 0.50524028 | I71: =I69-I57 -> -11917.779 | J71: =J69-J57 -> -13060.61 | K71: =K69-K57 -> -13582.874 | L71: =L69-L57 -> -13608.685 | M71: =M69-M57 -> -13237.332 | N71: =N69-N57 -> -12548.249
A74: Cash Flow Statement
A76: Operating Cash Flow
A77: Net Earnings | I77: 47915.919 | J77: 56732.007 | K77: 66545.964 | L77: 76581.46 | M77: 83351.537 | N77: 88469.862
A78: Plus: Depreciation & Amortization | I78: 12611.2 | J78: 14238.96 | K78: 15541.168 | L78: 16582.934 | M78: 17416.348 | N78: 18083.078
A79: Less: Changes in Working Capital | I79: 148442.47 | J79: 6607.699 | K79: 7431.7886 | L79: 4162.2142 | M79: 3932.5342 | N79: 3183.6052
A80: Cash from Operations | I80: =I77+I78-I79 -> -87915.353 | J80: =J77+J78-J79 -> 64363.268 | K80: =K77+K78-K79 -> 74655.343 | L80: =L77+L78-L79 -> 89002.18 | M80: =M77+M78-M79 -> 96835.351 | N80: =N77+N78-N79 -> 103369.33
A82: Investing Cash Flow
A83: Investments in Property & Equipment | I83: =-I110 -> -20750 | J83: =-J110 -> -20750 | K83: =-K110 -> -20750 | L83: =-L110 -> -20750 | M83: =-M110 -> -20750 | N83: =-N110 -> -20750
A84: Investments in Businesses
A85: Cash from Investing | I85: =SUM(I83:I84) -> -20750 | J85: =SUM(J83:J84) -> -20750 | K85: =SUM(K83:K84) -> -20750 | L85: =SUM(L83:L84) -> -20750 | M85: =SUM(M83:M84) -> -20750 | N85: =SUM(N83:N84) -> -20750
A87: Financing Cash Flow
A88: Issuance (repayment) of debt | I88: =I142 -> 0 | J88: =J142 -> 0 | K88: =K142 -> -20000 | L88: =L142 -> 0 | M88: =M142 -> 0 | N88: =N142 -> -10000
A89: Issuance (repayment) of equity | I89: =+I27 -> 0 | J89: =+J27 -> 0 | K89: =+K27 -> 0 | L89: =+L27 -> 0 | M89: =+M27 -> 0 | N89: =+N27 -> 0
A90: Payment of Dividends | I90: =-I28 -> 0 | J90: =-J28 -> 0 | K90: =-K28 -> 0 | L90: =-L28 -> -500 | M90: =-M28 -> -500 | N90: =-N28 -> -500
A91: Cash from Financing | I91: =SUM(I88:I90) -> 0 | J91: =SUM(J88:J90) -> 0 | K91: =SUM(K88:K90) -> -20000 | L91: =SUM(L88:L90) -> -500 | M91: =SUM(M88:M90) -> -500 | N91: =SUM(N88:N90) -> -10500
A93: Net Increase (decrease) in Cash | I93: =SUM(I80+I85+I91) -> -108665.35 | J93: =SUM(J80+J85+J91) -> 43613.268 | K93: =SUM(K80+K85+K91) -> 33905.343 | L93: =SUM(L80+L85+L91) -> 67752.18 | M93: =SUM(M80+M85+M91) -> 75585.351 | N93: =SUM(N80+N85+N91) -> 72119.335
A94: Opening Cash Balance | I94: =+H95 -> 615185.86 | J94: =+I95 -> 506520.51 | K94: =+J95 -> 550133.78 | L94: =+K95 -> 584039.12 | M94: =+L95 -> 651791.3 | N94: =+M95 -> 727376.65
A95: Closing Cash Balance | H95: =H51 -> 615185.86 | I95: =SUM(I93:I94) -> 506520.51 | J95: =SUM(J93:J94) -> 550133.78 | K95: =SUM(K93:K94) -> 584039.12 | L95: =SUM(L93:L94) -> 651791.3 | M95: =SUM(M93:M94) -> 727376.65 | N95: =SUM(N93:N94) -> 799495.99
A99: Supporting Schedules
A101: Working Capital Schedule
A102: Accounts Receivable | H102: =+H52 -> 24629.057 | I102: =+I52 -> 12967.525 | J102: =+J52 -> 14585.08 | K102: =+K52 -> 16240.522 | L102: =+L52 -> 17842.911 | M102: =+M52 -> 19248.645 | N102: =+N52 -> 20503.791
A103: Inventory | H103: =+H53 -> -127126.97 | I103: =+I53 -> 24206.046 | J103: =+J53 -> 30567.555 | K103: =+K53 -> 37741.651 | L103: =+L53 -> 41804.865 | M103: =+M53 -> 45815.659 | N103: =+N53 -> 48876.706
A104: Accounts Payable | H104: =+H61 -> 19966.288 | I104: =+I61 -> 11195.296 | J104: =+J61 -> 12566.661 | K104: =+K61 -> 13964.411 | L104: =+L61 -> 15467.8 | M104: =+M61 -> 16951.794 | N104: =+N61 -> 18084.381
A105: Net Working Capital (NWC) | H105: =+H102+H103-H104 -> -122464.2 | I105: =+I102+I103-I104 -> 25978.274 | J105: =+J102+J103-J104 -> 32585.973 | K105: =+K102+K103-K104 -> 40017.762 | L105: =+L102+L103-L104 -> 44179.976 | M105: =+M102+M103-M104 -> 48112.51 | N105: =+N102+N103-N104 -> 51296.115
A106: Change in NWC | I106: =+I105-H105 -> 148442.47 | J106: =+J105-I105 -> 6607.699 | K106: =+K105-J105 -> 7431.7886 | L106: =+L105-K105 -> 4162.2142 | M106: =+M105-L105 -> 3932.5342 | N106: =+N105-M105 -> 3183.6052
A108: Depreciation Schedule
A109: PPE Opening | I109: -1586.4 | J109: 19480.88 | K109: 36334.704 | L109: =K112 -> 49817.763 | M109: =L112 -> 60604.211 | N109: =M112 -> 69233.368
A110: Plus Capex | I110: 20750 | J110: 20750 | K110: 20750 | L110: 20750 | M110: 20750 | N110: 20750
A111: Less Depreciation | I111: =I109*0.2 -> -317.28 | J111: =J109*0.2 -> 3896.176 | K111: =K109*0.2 -> 7266.9408 | L111: =L109*0.2 -> 9963.5526 | M111: =M109*0.2 -> 12120.842 | N111: =N109*0.2 -> 13846.674
A112: PPE Closing | H112: -1586.4 | I112: =+I109+I110-I111 -> 19480.88 | J112: =+J109+J110-J111 -> 36334.704 | K112: =+K109+K110-K111 -> 49817.763 | L112: =+L109+L110-L111 -> 60604.211 | M112: =+M109+M110-M111 -> 69233.368 | N112: =+N109+N110-N111 -> 76136.695
A114: Debt Schedule
A115: Senior Debt A
A116: Opening Balance | I116: =100000*I12 -> 25000 | J116: =100000*J12 -> 25000 | K116: =100000*K12 -> 25000 | L116: =100000*L12 -> 25000 | M116: - | N116: =+M118 -> 0
A117: Addition (Repayment) | I117: =-$H$118*I12 -> 0 | J117: =-$H$118*J12 -> 0 | K117: =-$H$118*K12 -> 0 | L117: =-$H$118*L12 -> 0 | M117: =-$H$118*M12 -> 0 | N117: =-$H$118*N12 -> 0
A118: Closing Balance | H118: =+'M&A Assumptions & Analysis'!H20 -> 0 | I118: =SUM(I116:I117) -> 25000 | J118: =SUM(J116:J117) -> 25000 | K118: =SUM(K116:K117) -> 25000 | L118: =SUM(L116:L117) -> 25000 | M118: =SUM(M116:M117) -> 0 | N118: =SUM(N116:N117) -> 0
A119: Interest | I119: =I118*0.08 -> 2000 | J119: =J118*0.08 -> 2000 | K119: =K118*0.08 -> 2000 | L119: =L118*0.08 -> 2000 | M119: =M118*0.08 -> 0 | N119: =N118*0.08 -> 0
A120: Senior Debt B
A121: Opening Balance | I121: =+H123 -> 0 | J121: =50000*J13 -> 10000 | K121: =50000*K13 -> 10000 | L121: =50000*L13 -> 10000 | M121: =50000*M13 -> 10000 | N121: =50000*N13 -> 10000
A122: Addition (Repayment) | I122: =-$H$123*I13 -> 0 | J122: =-$H$123*J13 -> 0 | K122: - | L122: =-$H$123*L13 -> 0 | M122: =-$H$123*M13 -> 0 | N122: =-$H$123*N13 -> 0
A123: Closing Balance | H123: =+'M&A Assumptions & Analysis'!H21 -> 0 | I123: =SUM(I121:I122) -> 0 | J123: =SUM(J121:J122) -> 10000 | K123: =SUM(K121:K122) -> 10000 | L123: =SUM(L121:L122) -> 10000 | M123: =SUM(M121:M122) -> 10000 | N123: =SUM(N121:N122) -> 10000
A124: Interest | J124: =J123*0.08 -> 800 | K124: =K123*0.08 -> 800 | L124: =L123*0.08 -> 800 | M124: =M123*0.08 -> 800 | N124: =N123*0.08 -> 800
A125: Subordinated Debt
A126: Opening Balance | I126: =+H128 -> 0 | J126: =+I128 -> 0 | K126: =+J128 -> 0 | L126: =+K128 -> 0 | M126: =+L128 -> 0 | N126: =25000*100% -> 25000
A127: Addition (Repayment) | I127: =-$H$128*I14 -> 0 | J127: =-$H$128*J14 -> 0 | K127: =-$H$128*K14 -> 0 | L127: =-$H$128*L14 -> 0 | M127: =-$H$128*M14 -> 0 | N127: =-$H$128*N14 -> 0
A128: Closing Balance | H128: =+'M&A Assumptions & Analysis'!H22 -> 0 | I128: =SUM(I126:I127) -> 0 | J128: =SUM(J126:J127) -> 0 | K128: =SUM(K126:K127) -> 0 | L128: =SUM(L126:L127) -> 0 | M128: =SUM(M126:M127) -> 0 | N128: =SUM(N126:N127) -> 25000
...

Sheet Acquirer Model
D1: Historical Results | I1: Forecast Period | O1: Stub
A2: ='M&A Assumptions & Analysis'!D6& " Model" -> Online Company Inc Model | D2: 2020 | E2: =+D2+1 -> 2021 | F2: =+E2+1 -> 2022 | G2: =+F2+1 -> 2023 | H2: =+G2+1 -> 2024 | I2: =+H2+1 -> 2025 | J2: =+I2+1 -> 2026 | K2: =+J2+1 -> 2027 | L2: =+K2+1 -> 2028 | ... N2: =+M2+1 -> 2030 | O2: =+O4 -> 45838 | P2: =+P4 -> 46203
A3: Balance Sheet Check | D3: =IFERROR(IF(ABS(D101)>1,"ERROR","ok"),"ok") -> ok | E3: =IFERROR(IF(ABS(E101)>1,"ERROR","ok"),"ok") -> ok | F3: =IFERROR(IF(ABS(F101)>1,"ERROR","ok"),"ok") -> ok | G3: =IFERROR(IF(ABS(G101)>1,"ERROR","ok"),"ok") -> ok | H3: =IFERROR(IF(ABS(H101)>1,"ERROR","ok"),"ok") -> ok | I3: =IFERROR(IF(ABS(I101)>1,"ERROR","ok"),"ok") -> ok | J3: =IFERROR(IF(ABS(J101)>1,"ERROR","ok"),"ok") -> ok | K3: =IFERROR(IF(ABS(K101)>1,"ERROR","ok"),"ok") -> ok | ... N3: =IFERROR(IF(ABS(N101)>1,"ERROR","ok"),"ok") -> ok
A4: End of Period | D4: 44196 | E4: =EOMONTH(D4,12) -> 44561 | F4: =EOMONTH(E4,12) -> 44926 | G4: =EOMONTH(F4,12) -> 45291 | H4: =EOMONTH(G4,12) -> 45657 | I4: =EOMONTH(H4,12) -> 46022 | J4: =EOMONTH(I4,12) -> 46387 | K4: =EOMONTH(J4,12) -> 46752 | L4: =EOMONTH(K4,12) -> 47118 | ... N4: =EOMONTH(M4,12) -> 47848 | O4: =+'M&A Assumptions & Analysis'!D10 -> 45838 | P4: =+EOMONTH(O4,P6*12) -> 46203
A5: Days in Period | D5: 366 | E5: =E4-D4 -> 365 | F5: =F4-E4 -> 365 | G5: =G4-F4 -> 365 | H5: =H4-G4 -> 366 | I5: =I4-H4 -> 365 | J5: =J4-I4 -> 365 | K5: =K4-J4 -> 365 | L5: 365 | M5: =M4-L4 -> 365 | N5: =N4-M4 -> 365 | O5: 365 | P5: 365
A6: Fraction of Year | D6: 1 | E6: =D6 -> 1 | F6: =E6 -> 1 | G6: =F6 -> 1 | H6: =G6 -> 1 | I6: =H6 -> 1 | J6: =I6 -> 1 | K6: =J6 -> 1 | L6: =K6 -> 1 | ... N6: =M6 -> 1 | O6: 1 | P6: 1
A8: Assumptions
H10: LIVE SCENARIO | I10: 1
A12: SCENARIO 1
A13: Revenue Growth (% Change) | I13: 0.1 | J13: 0.1 | K13: 0.1 | L13: 0.09 | M13: 0.08 | N13: 0.07 | O13: 0.1 | P13: 0.1
A14: Cost of Goods Sold (% of Revenue) | I14: 0.42 | J14: 0.43 | K14: 0.44 | L14: 0.45 | M14: 0.46 | N14: 0.46 | O14: 0.42 | P14: 0.42
A15: Salaries and Benefits (% of Revenue) | I15: 0.17 | J15: 0.17 | K15: 0.17 | L15: 0.17 | M15: 0.17 | N15: 0.17 | O15: 0.17 | P15: 0.17
A16: Rent and Overhead ($000's) | I16: 15000 | J16: 15000 | K16: 15000 | L16: 15000 | M16: 15000 | N16: 15000 | O16: 15000 | P16: 15000
A17: Depreciation & Amortization (% of PP&E) | I17: 0.2 | J17: 0.2 | K17: 0.2 | L17: 0.2 | M17: 0.2 | N17: 0.2 | O17: 0.2 | P17: 0.2
A18: Interest (% of Debt) | I18: 0.1 | J18: 0.1 | K18: 0.1 | L18: 0.1 | M18: 0.1 | N18: 0.1 | O18: 0.1 | P18: 0.1
A19: Tax Rate (% of Earnings Before Tax) | I19: 0.28 | J19: 0.28 | K19: 0.28 | L19: 0.28 | M19: 0.28 | N19: 0.28 | O19: 0.28 | P19: 0.28
A20: Accounts Receivable (Days) | I20: 18 | J20: 18 | K20: 18 | L20: 18 | M20: 18 | N20: 18 | O20: 18 | P20: 18
A21: Inventory (Days) | I21: 80 | J21: 90 | K21: 100 | L21: 100 | M21: 100 | N21: 100 | O21: 80 | P21: 80
A22: Accounts Payable (Days) | I22: 37 | J22: 37 | K22: 37 | L22: 37 | M22: 37 | N22: 37 | O22: 37 | P22: 37
A23: Capital Expenditures ($000's) | I23: 15000 | J23: 15000 | K23: 15000 | L23: 15000 | M23: 15000 | N23: 15000 | O23: 15000 | P23: 15000
A24: Debt Issuance (Repayment) ($000's) | I24: 0 | J24: 0 | K24: -20000 | L24: 0 | M24: 0 | N24: 0 | O24: 0 | P24: 0
... A26: Payment of Dividends | I26: 0 | J26: 0 | K26: 0 | L26: 0 | M26: 200 | N26: 200 | O26: 0 | P26: 0
A28: SCENARIO 2
A29: Revenue Growth (% Change) | I29: 0.05 | J29: 0.045 | K29: 0.04 | L29: 0.035 | M29: 0.03 | N29: 0.03 | O29: 0.05 | P29: 0.05
A30: Cost of Goods Sold (% of Revenue) | I30: 0.37 | J30: 0.37 | K30: 0.36 | L30: 0.36 | M30: 0.35 | N30: 0.35 | O30: 0.37 | P30: 0.37
A31: Salaries and Benefits (% of Revenue) | I31: 0.17 | J31: 0.17 | K31: 0.17 | L31: 0.17 | M31: 0.17 | N31: 0.17 | O31: 0.17 | P31: 0.17
A32: Rent and Overhead ($000's) | I32: 10000 | J32: 10000 | K32: 10000 | L32: 10000 | M32: 10000 | N32: 10000 | O32: 10000 | P32: 10000
A33: Depreciation & Amortization (% of PP&E) | I33: 0.2 | J33: 0.2 | K33: 0.2 | L33: 0.2 | M33: 0.2 | N33: 0.2 | O33: 0.2 | P33: 0.2
A34: Interest (% of Debt) | I34: 0.05 | J34: 0.05 | K34: 0.05 | L34: 0.05 | M34: 0.05 | N34: 0.05 | O34: 0.05 | P34: 0.05
A35: Tax Rate (% of Earnings Before Tax) | I35: 0.28 | J35: 0.28 | K35: 0.28 | L35: 0.28 | M35: 0.28 | N35: 0.28 | O35: 0.28 | P35: 0.28
A36: Accounts Receivable (Days) | I36: 18 | J36: 18 | K36: 18 | L36: 18 | M36: 18 | N36: 18 | O36: 18 | P36: 18
A37: Inventory (Days) | I37: 73 | J37: 73 | K37: 73 | L37: 73 | M37: 73 | N37: 73 | O37: 73 | P37: 73
A38: Accounts Payable (Days) | I38: 37 | J38: 37 | K38: 37 | L38: 37 | M38: 37 | N38: 37 | O38: 37 | P38: 37
A39: Capital Expenditures ($000's) | I39: 15000 | J39: 15000 | K39: 15000 | L39: 15000 | M39: 15000 | N39: 15000 | O39: 15000 | P39: 15000
A40: Debt Issuance (Repayment) ($000's) | I40: 0 | J40: 0 | K40: -20000 | L40: 0 | M40: 0 | N40: 0 | O40: 0 | P40: 0
... A42: Payment of Dividends | I42: 0 | J42: 0 | K42: 0 | L42: 0 | M42: 100 | N42: 100 | O42: 0 | P42: 0
A44: LIVE SCENARIO
A45: Revenue Growth (% Change) | I45: =CHOOSE($I$10,I13,I29) -> 0.1 | J45: =CHOOSE($I$10,J13,J29) -> 0.1 | K45: =CHOOSE($I$10,K13,K29) -> 0.1 | L45: =CHOOSE($I$10,L13,L29) -> 0.09 | M45: =CHOOSE($I$10,M13,M29) -> 0.08 | N45: =CHOOSE($I$10,N13,N29) -> 0.07 | O45: =CHOOSE($I$10,O13,O29) -> 0.1 | P45: =CHOOSE($I$10,P13,P29) -> 0.1
A46: Cost of Goods Sold (% of Revenue) | I46: =CHOOSE($I$10,I14,I30) -> 0.42 | J46: =CHOOSE($I$10,J14,J30) -> 0.43 | K46: =CHOOSE($I$10,K14,K30) -> 0.44 | L46: =CHOOSE($I$10,L14,L30) -> 0.45 | M46: =CHOOSE($I$10,M14,M30) -> 0.46 | N46: =CHOOSE($I$10,N14,N30) -> 0.46 | O46: =CHOOSE($I$10,O14,O30) -> 0.42 | P46: =CHOOSE($I$10,P14,P30) -> 0.42
A47: Marketing, Advertising & Promotion (% of Revenue) | I47: =CHOOSE($I$10,I15,I31) -> 0.17 | J47: =CHOOSE($I$10,J15,J31) -> 0.17 | K47: =CHOOSE($I$10,K15,K31) -> 0.17 | L47: =CHOOSE($I$10,L15,L31) -> 0.17 | M47: =CHOOSE($I$10,M15,M31) -> 0.17 | N47: =CHOOSE($I$10,N15,N31) -> 0.17 | O47: =CHOOSE($I$10,O15,O31) -> 0.17 | P47: =CHOOSE($I$10,P15,P31) -> 0.17
A48: General & Administrative ($000's) | I48: =CHOOSE($I$10,I16,I32) -> 15000 | J48: =CHOOSE($I$10,J16,J32) -> 15000 | K48: =CHOOSE($I$10,K16,K32) -> 15000 | L48: =CHOOSE($I$10,L16,L32) -> 15000 | M48: =CHOOSE($I$10,M16,M32) -> 15000 | N48: =CHOOSE($I$10,N16,N32) -> 15000 | O48: =CHOOSE($I$10,O16,O32) -> 15000 | P48: =CHOOSE($I$10,P16,P32) -> 15000
A49: Depreciation & Amortization (% of PP&E) | I49: =CHOOSE($I$10,I17,I33) -> 0.2 | J49: =CHOOSE($I$10,J17,J33) -> 0.2 | K49: =CHOOSE($I$10,K17,K33) -> 0.2 | L49: =CHOOSE($I$10,L17,L33) -> 0.2 | M49: =CHOOSE($I$10,M17,M33) -> 0.2 | N49: =CHOOSE($I$10,N17,N33) -> 0.2 | O49: =CHOOSE($I$10,O17,O33) -> 0.2 | P49: =CHOOSE($I$10,P17,P33) -> 0.2
A50: Interest (% of Debt) | I50: =CHOOSE($I$10,I18,I34) -> 0.1 | J50: =CHOOSE($I$10,J18,J34) -> 0.1 | K50: =CHOOSE($I$10,K18,K34) -> 0.1 | L50: =CHOOSE($I$10,L18,L34) -> 0.1 | M50: =CHOOSE($I$10,M18,M34) -> 0.1 | N50: =CHOOSE($I$10,N18,N34) -> 0.1 | O50: =CHOOSE($I$10,O18,O34) -> 0.1 | P50: =CHOOSE($I$10,P18,P34) -> 0.1
A51: Tax Rate (% of Earnings Before Tax) | I51: =CHOOSE($I$10,I19,I35) -> 0.28 | J51: =CHOOSE($I$10,J19,J35) -> 0.28 | K51: =CHOOSE($I$10,K19,K35) -> 0.28 | L51: =CHOOSE($I$10,L19,L35) -> 0.28 | M51: =CHOOSE($I$10,M19,M35) -> 0.28 | N51: =CHOOSE($I$10,N19,N35) -> 0.28 | O51: =CHOOSE($I$10,O19,O35) -> 0.28 | P51: =CHOOSE($I$10,P19,P35) -> 0.28
A52: Accounts Receivable (Days) | I52: =CHOOSE($I$10,I20,I36) -> 18 | J52: =CHOOSE($I$10,J20,J36) -> 18 | K52: =CHOOSE($I$10,K20,K36) -> 18 | L52: =CHOOSE($I$10,L20,L36) -> 18 | M52: =CHOOSE($I$10,M20,M36) -> 18 | N52: =CHOOSE($I$10,N20,N36) -> 18 | O52: =CHOOSE($I$10,O20,O36) -> 18 | P52: =CHOOSE($I$10,P20,P36) -> 18
A53: Inventory (Days) | I53: =CHOOSE($I$10,I21,I37) -> 80 | J53: =CHOOSE($I$10,J21,J37) -> 90 | K53: =CHOOSE($I$10,K21,K37) -> 100 | L53: =CHOOSE($I$10,L21,L37) -> 100 | M53: =CHOOSE($I$10,M21,M37) -> 100 | N53: =CHOOSE($I$10,N21,N37) -> 100 | O53: =CHOOSE($I$10,O21,O37) -> 80 | P53: =CHOOSE($I$10,P21,P37) -> 80
A54: Accounts Payable (Days) | I54: =CHOOSE($I$10,I22,I38) -> 37 | J54: =CHOOSE($I$10,J22,J38) -> 37 | K54: =CHOOSE($I$10,K22,K38) -> 37 | L54: =CHOOSE($I$10,L22,L38) -> 37 | M54: =CHOOSE($I$10,M22,M38) -> 37 | N54: =CHOOSE($I$10,N22,N38) -> 37 | O54: =CHOOSE($I$10,O22,O38) -> 37 | P54: =CHOOSE($I$10,P22,P38) -> 37
A55: Capital Expenditures ($000's) | I55: =CHOOSE($I$10,I23,I39) -> 15000 | J55: =CHOOSE($I$10,J23,J39) -> 15000 | K55: =CHOOSE($I$10,K23,K39) -> 15000 | L55: =CHOOSE($I$10,L23,L39) -> 15000 | M55: =CHOOSE($I$10,M23,M39) -> 15000 | N55: =CHOOSE($I$10,N23,N39) -> 15000 | O55: =CHOOSE($I$10,O23,O39) -> 15000 | P55: =CHOOSE($I$10,P23,P39) -> 15000
A56: Debt Issuance (Repayment) ($000's) | I56: =CHOOSE($I$10,I24,I40) -> 0 | J56: =CHOOSE($I$10,J24,J40) -> 0 | K56: =CHOOSE($I$10,K24,K40) -> -20000 | L56: =CHOOSE($I$10,L24,L40) -> 0 | M56: =CHOOSE($I$10,M24,M40) -> 0 | N56: =CHOOSE($I$10,N24,N40) -> 0 | O56: =CHOOSE($I$10,O24,O40) -> 0 | P56: =CHOOSE($I$10,P24,P40) -> 0
... A58: Payment of Dividends | I58: =CHOOSE($I$10,I26,I42) -> 0 | J58: =CHOOSE($I$10,J26,J42) -> 0 | K58: =CHOOSE($I$10,K26,K42) -> 0 | L58: =CHOOSE($I$10,L26,L42) -> 0 | M58: =CHOOSE($I$10,M26,M42) -> 200 | N58: =CHOOSE($I$10,N26,N42) -> 200 | O58: =CHOOSE($I$10,O26,O42) -> 0 | P58: =CHOOSE($I$10,P26,P42) -> 0
A61: Income Statement
A63: Revenue | D63: 102007 | E63: 118086 | F63: 131345 | G63: 142341 | H63: 150772 | I63: =H63*1.1 -> 165849.2 | J63: =I63*1.1 -> 182434.12 | K63: =J63*1.1 -> 200677.53 | L63: =K63*1.09 -> 218738.51 | M63: =L63*1.08 -> 236237.59 | N63: =M63*1.07 -> 252774.22 | O63: =N63*1.1 -> 278051.64 | P63: =O63*1.1 -> 305856.81
A64: Cost of Goods Sold (COGS) | D64: 39023 | E64: 48004 | F64: 49123 | G64: 52654 | H64: 56710 | I64: =I63*I46 -> 69656.664 | J64: =J63*(J46) -> 78446.672 | K64: =K63*(K46) -> 88298.114 | L64: =L63*(L46) -> 98432.329 | M64: =M63*(M46) -> 108669.29 | N64: =N63*(N46) -> 116276.14 | O64: =O63*O46 -> 116781.69 | P64: =P63*P46 -> 128459.86
A65: Gross Profit | D65: =D63-D64 -> 62984 | E65: =E63-E64 -> 70082 | F65: =F63-F64 -> 82222 | G65: =G63-G64 -> 89687 | H65: =H63-H64 -> 94062 | I65: =I63-I64 -> 96192.536 | J65: =J63-J64 -> 103987.45 | K65: =K63-K64 -> 112379.42 | ... P65: =P63-P64 -> 177396.95
A66: Expenses
A67: Marketing, Advertising & Promotion | D67: 26427 | E67: 22658 | F67: 23872 | G67: 23002 | H67: 25245 | I67: =I63*I47 -> 28194.364 | J67: =J63*J47 -> 31013.8 | K67: =K63*K47 -> 34115.18 | L67: =L63*L47 -> 37185.547 | M67: =M63*M47 -> 40160.39 | N67: =N63*N47 -> 42971.618 | O67: =O63*O47 -> 47268.78 | P67: =P63*P47 -> 51995.657
A68: General & Administrative | D68: 10963 | E68: 10125 | F68: 10087 | G68: 11020 | H68: 11412 | I68: =I48 -> 15000 | J68: =J48 -> 15000 | K68: =K48 -> 15000 | L68: =L48 -> 15000 | M68: =M48 -> 15000 | N68: =N48 -> 15000 | O68: =O48 -> 15000 | P68: =P48 -> 15000
A69: Depreciation & Amortization | D69: 19500 | E69: 18150 | F69: 17205 | G69: 16543.5 | H69: 16080.45 | I69: 7504.21 | J69: 9003.368 | K69: 10202.694 | L69: 11162.156 | M69: 11929.724 | N69: 12543.78 | O69: 13035 | P69: 13428
A70: Interest | D70: 2500 | E70: 2500 | F70: 1500 | G70: 1500 | H70: 1500 | I70: =I148 -> 3000 | J70: =J148 -> 3000 | K70: =K148 -> 1000 | L70: =L148 -> 1000 | M70: =M148 -> 1000 | N70: =N148 -> 1000 | O70: =O148 -> 1000 | P70: =P148 -> 1000
A71: Total Expenses | D71: =SUM(D67:D70) -> 59390 | E71: =SUM(E67:E70) -> 53433 | F71: =SUM(F67:F70) -> 52664 | G71: =SUM(G67:G70) -> 52065.5 | H71: =SUM(H67:H70) -> 54237.45 | I71: =SUM(I67:I70) -> 53698.574 | J71: =SUM(J67:J70) -> 58017.168 | K71: =SUM(K67:K70) -> 60317.875 | ... P71: =SUM(P67:P70) -> 81423.657
A72: Earnings Before Tax | D72: =D65-D71 -> 3594 | E72: =E65-E71 -> 16649 | F72: =F65-F71 -> 29558 | G72: =G65-G71 -> 37621.5 | H72: =H65-H71 -> 39824.55 | I72: =I65-I71 -> 42493.962 | J72: =J65-J71 -> 45970.28 | K72: =K65-K71 -> 52061.543 | ... P72: =P65-P71 -> 95973.292
A74: Taxes | D74: 1120.1708 | E74: 4858.2165 | F74: 8482.8061 | G74: 10908.021 | H74: 11597.665 | I74: =I72*0.28 -> 11898.309 | J74: =J72*0.28 -> 12871.678 | K74: =K72*0.28 -> 14577.232 | L74: =L72*0.28 -> 15668.374 | M74: =M72*0.28 -> 16653.892 | N74: =N72*0.28 -> 18195.151 | O74: =O72*0.28 -> 23790.529 | P74: =P72*0.28 -> 26872.522
A75: Net Earnings | D75: =D72-D74 -> 2473.8292 | E75: =E72-E74 -> 11790.783 | F75: =F72-F74 -> 21075.194 | G75: =G72-G74 -> 26713.479 | H75: =H72-H74 -> 28226.885 | I75: =I72-I74 -> 30595.653 | J75: =J72-J74 -> 33098.602 | K75: =K72-K74 -> 37484.311 | ... P75: =P72-P74 -> 69100.77
A78: Balance Sheet
A80: Assets
A81: Cash | D81: 67971.179 | E81: 81209.913 | F81: 83715.257 | G81: 111069.34 | H81: 139549.52 | I81: 159473.86 | J81: 182573.31 | K81: 190511.04 | L81: 224323.42 | M81: 261247.54 | N81: 303250.39 | O81: 367525.83 | P81: 432307.77
A82: Accounts Receivable | D82: 5100.35 | E82: 5904.3 | F82: 6567.25 | G82: 7117.05 | H82: 7538.6 | I82: =I63*I52/365 -> 8178.8647 | J82: =J63*J52/365 -> 8996.7511 | K82: =K63*K52/365 -> 9896.4262 | L82: =L63*L52/365 -> 10787.105 | M82: =M63*M52/365 -> 11650.073 | N82: =N63*N52/365 -> 12465.578 | O82: =O63*O52/365 -> 13712.136 | P82: =P63*P52/365 -> 15083.349
A83: Inventory | D83: 7804.6 | E83: 9600.8 | F83: 9824.6 | G83: 10530.8 | H83: 11342 | I83: =I64*I53/365 -> 15267.214 | J83: =J64*J53/365 -> 19343.015 | K83: =K64*K53/365 -> 24191.264 | L83: =L64*L53/365 -> 26967.761 | M83: =M64*M53/365 -> 29772.409 | N83: =N64*N53/365 -> 31856.477 | O83: =O64*O53/365 -> 25595.987 | P83: =P64*P53/365 -> 28155.586
A84: Current Assets | D84: =SUM(D81:D83) -> 80876.129 | E84: =SUM(E81:E83) -> 96715.013 | F84: =SUM(F81:F83) -> 100107.11 | G84: =SUM(G81:G83) -> 128717.19 | H84: =SUM(H81:H83) -> 158430.12 | I84: =SUM(I81:I83) -> 182919.93 | J84: =SUM(J81:J83) -> 210913.08 | K84: =SUM(K81:K83) -> 224598.73 | ... P84: =SUM(P81:P83) -> 475546.71
A85: Property & Equipment | D85: 45500 | E85: 42350 | F85: 40145 | G85: 38601.5 | H85: 37521.05 | I85: 45016.84 | J85: 51013.472 | K85: 55810.778 | L85: 59648.622 | M85: 62718.898 | N85: 65175.118 | O85: 67140 | P85: 68712
A86: Goodwill
A87: Total Assets | D87: =SUM(D84:D86) -> 126376.13 | E87: =SUM(E84:E86) -> 139065.01 | F87: =SUM(F84:F86) -> 140252.11 | G87: =SUM(G84:G86) -> 167318.69 | H87: =SUM(H84:H86) -> 195951.17 | I87: =SUM(I84:I86) -> 227936.77 | J87: =SUM(J84:J86) -> 261926.55 | K87: =SUM(K84:K86) -> 280409.5 | ... P87: =SUM(P84:P86) -> 544258.71
A89: Liabilities
A90: Short Term Debt
A91: Accounts Payable | D91: 3902.3 | E91: 4800.4 | F91: 4912.3 | G91: 5265.4 | H91: 5671 | I91: =I64*I54/365 -> 7061.0865 | J91: =J64*J54/365 -> 7952.1284 | K91: =K64*K54/365 -> 8950.7677 | L91: =L64*L54/365 -> 9978.0718 | M91: =M64*M54/365 -> 11015.791 | N91: =N64*N54/365 -> 11786.897 | O91: =O64*O54/365 -> 11838.144 | P91: =P64*P54/365 -> 13021.958
A92: Current Liabilities | D92: =SUM(D90:D91) -> 3902.3 | E92: =SUM(E90:E91) -> 4800.4 | F92: =SUM(F90:F91) -> 4912.3 | G92: =SUM(G90:G91) -> 5265.4 | H92: =SUM(H90:H91) -> 5671 | I92: =SUM(I90:I91) -> 7061.0865 | J92: =SUM(J90:J91) -> 7952.1284 | K92: =SUM(K90:K91) -> 8950.7677 | ... P92: =SUM(P90:P91) -> 13021.958
A93: Long Term Debt | D93: 50000 | E93: 50000 | F93: 30000 | G93: 30000 | H93: 30000 | I93: 30000 | J93: 30000 | K93: 10000 | L93: 10000 | M93: 10000 | N93: 10000 | O93: 10000 | P93: 10000
A94: Total Liabilities | D94: =SUM(D92:D93) -> 53902.3 | E94: =SUM(E92:E93) -> 54800.4 | F94: =SUM(F92:F93) -> 34912.3 | G94: =SUM(G92:G93) -> 35265.4 | H94: =SUM(H92:H93) -> 35671 | I94: =SUM(I92:I93) -> 37061.086 | J94: =SUM(J92:J93) -> 37952.128 | K94: =SUM(K92:K93) -> 18950.768 | ... P94: =SUM(P92:P93) -> 23021.958
A95: Shareholder's Equity
A96: Equity Capital | D96: 70000 | E96: 70000 | F96: 70000 | G96: 70000 | H96: 70000 | I96: =H96+I57 -> 70000 | J96: =I96+J57 -> 70000 | K96: =J96+K57 -> 70000 | L96: =K96+L57 -> 70000 | M96: =L96+M57 -> 70000 | N96: =M96+N57 -> 70000 | O96: =H96+O57 -> 70000 | P96: =+I96 -> 70000
A97: Retained Earnings | D97: 2473.8292 | E97: 14264.613 | F97: 35339.807 | G97: 62053.286 | H97: 90280.17 | I97: =H97+I75-I58 -> 120875.82 | J97: =I97+J75-J58 -> 153974.42 | K97: =J97+K75-K58 -> 191458.74 | L97: =K97+L75-L58 -> 231748.84 | M97: =L97+M75-M58 -> 274373.13 | N97: =M97+N75-N58 -> 320960.66 | O97: =N97+O75-O58 -> 382136.31 | P97: =O97+P75-P58 -> 451237.08
A98: Shareholder's Equity | D98: =SUM(D96:D97) -> 72473.829 | E98: =SUM(E96:E97) -> 84264.613 | F98: =SUM(F96:F97) -> 105339.81 | G98: =SUM(G96:G97) -> 132053.29 | H98: =SUM(H96:H97) -> 160280.17 | I98: =SUM(I96:I97) -> 190875.82 | J98: =SUM(J96:J97) -> 223974.42 | K98: =SUM(K96:K97) -> 261458.74 | ... P98: =SUM(P96:P97) -> 521237.08
A99: Total Liabilities & Shareholder's Equity | D99: =D94+D98 -> 126376.13 | E99: =E94+E98 -> 139065.01 | F99: =F94+F98 -> 140252.11 | G99: =G94+G98 -> 167318.69 | H99: =H94+H98 -> 195951.17 | I99: =I98+I94 -> 227936.91 | J99: =J98+J94 -> 261926.55 | K99: =K98+K94 -> 280409.5 | L99: =L98+L94 -> 321726.91 | M99: =M98+M94 -> 365388.92 | N99: =N98+N94 -> 412747.56 | O99: =O98+O94 -> 473974.45 | P99: =P98+P94 -> 544259.04
A101: Check | D101: =D99-D87 -> 0 | E101: =E99-E87 -> 0 | F101: =F99-F87 -> 0 | G101: =G99-G87 -> 0 | H101: =H99-H87 -> 0 | I101: =J99-J87 -> 0 | J101: =J99-J87 -> 0 | K101: =K99-K87 -> 0 | L101: =L99-L87 -> 0 | M101: =M99-M87 -> 0 | N101: =N99-N87 -> 0 | O101: =O99-O87 -> 0.50524028 | P101: =P99-P87 -> 0.3305037
A104: Cash Flow Statement
A106: Operating Cash Flow
A107: Net Earnings | D107: =D75 -> 2473.8292 | E107: =E75 -> 11790.783 | F107: =F75 -> 21075.194 | G107: =G75 -> 26713.479 | H107: =H75 -> 28226.885 | I107: =I75 -> 30595.653 | J107: =J75 -> 33098.602 | K107: =K75 -> 37484.311 | ... P107: =P75 -> 69100.77
A108: Plus: Depreciation & Amortization | D108: =D141 -> 19500 | E108: =E141 -> 18150 | F108: =F141 -> 17205 | G108: =G141 -> 16543.5 | H108: =H141 -> 16080.45 | I108: 7504.21 | J108: 9003.368 | K108: 10202.694 | L108: 11162.156 | M108: 11929.724 | N108: 12543.78 | O108: 13035 | P108: 13428
A109: Less: Changes in Working Capital | D109: 9002.65 | E109: 1702.05 | F109: 774.85 | G109: 902.9 | H109: 827.15 | I109: 3175.5275 | J109: 4002.5101 | K109: 4749.285 | L109: 2639.8717 | M109: 2629.8961 | N109: 2128.4683 | O109: -5065.1799 | P109: 2746.9979
A110: Cash from Operations | D110: =D107+D108-D109 -> 12971.179 | E110: =E107+E108-E109 -> 28238.733 | F110: =F107+F108-F109 -> 37505.344 | G110: =G107+G108-G109 -> 42354.079 | H110: =H107+H108-H109 -> 43480.185 | I110: =I107+I108-I109 -> 34924.335 | J110: =J107+J108-J109 -> 38099.459 | K110: =K107+K108-K109 -> 42937.72 | ... P110: =P107+P108-P109 -> 79781.772
A112: Investing Cash Flow
A113: Investments in Property & Equipment | D113: =-D140 -> -15000 | E113: =-E140 -> -15000 | F113: =-F140 -> -15000 | G113: =-G140 -> -15000 | H113: =-H140 -> -15000 | I113: =-I140 -> -15000 | J113: =-J140 -> -15000 | K113: =-K140 -> -15000 | ... P113: =-P140 -> -15000
A114: Investments in Businesses
A115: Cash from Investing | D115: =SUM(D113:D114) -> -15000 | E115: =SUM(E113:E114) -> -15000 | F115: =SUM(F113:F114) -> -15000 | G115: =SUM(G113:G114) -> -15000 | H115: =SUM(H113:H114) -> -15000 | I115: =SUM(I113:I114) -> -15000 | J115: =SUM(J113:J114) -> -15000 | K115: =SUM(K113:K114) -> -15000 | ... P115: =SUM(P113:P114) -> -15000
A117: Financing Cash Flow
A118: Issuance (repayment) of debt | D118: 0 | E118: 0 | F118: -20000 | G118: 0 | H118: 0 | I118: =I146 -> 0 | J118: =J146 -> 0 | K118: =K146 -> -20000 | L118: =L146 -> 0 | M118: =M146 -> 0 | N118: =N146 -> 0 | O118: =O146 -> 0 | P118: =P146 -> 0
A119: Issuance (repayment) of equity | D119: - | E119: 0 | F119: 0 | G119: 0 | H119: 0 | I119: =I57 -> 0 | J119: =J57 -> 0 | K119: =K57 -> 0 | L119: =L57 -> 0 | M119: =M57 -> 0 | N119: =N57 -> 0 | O119: =O57 -> 0 | P119: =P57 -> 0
A120: Payment of Dividends | D120: 0 | E120: 0 | F120: 0 | G120: 0 | H120: 0 | I120: =-I58 -> 0 | J120: =-J58 -> 0 | K120: =-K58 -> 0 | L120: =-L58 -> 0 | M120: =-M58 -> -200 | N120: =-N58 -> -200 | O120: =-O58 -> 0 | P120: =-P58 -> 0
A121: Cash from Financing | D121: =SUM(D118:D120) -> 0 | E121: =SUM(E118:E120) -> 0 | F121: =SUM(F118:F120) -> -20000 | G121: =SUM(G118:G120) -> 0 | H121: =SUM(H118:H120) -> 0 | I121: =SUM(I118:I120) -> 0 | J121: =SUM(J118:J120) -> 0 | K121: =SUM(K118:K120) -> -20000 | ... P121: =SUM(P118:P120) -> 0
A123: Net Increase (decrease) in Cash | D123: =D110+D115+D121 -> -2028.8208 | E123: =E110+E115+E121 -> 13238.733 | F123: =F110+F115+F121 -> 2505.3439 | G123: =G110+G115+G121 -> 27354.079 | H123: =H110+H115+H121 -> 28480.185 | I123: =I110+I115+I121 -> 19924.335 | J123: =J110+J115+J121 -> 23099.459 | K123: =K110+K115+K121 -> 7937.7205 | ... P123: =P110+P115+P121 -> 64781.772
...

Sheet Target Model
D1: Historical Results | I1: Forecast Period | O1: Stub
A2: ='M&A Assumptions & Analysis'!D7&" Model" -> Brick 'n' Mortar Co Model | D2: 2020 | E2: =+D2+1 -> 2021 | F2: =+E2+1 -> 2022 | G2: =+F2+1 -> 2023 | H2: =+G2+1 -> 2024 | I2: =+H2+1 -> 2025 | J2: =+I2+1 -> 2026 | K2: =+J2+1 -> 2027 | L2: =+K2+1 -> 2028 | ... N2: =+M2+1 -> 2030 | O2: =+O4 -> 45838 | P2: =+P4 -> 46203
A3: Balance Sheet Check | D3: =IFERROR(IF(ABS(D101)>1,"ERROR","ok"),"ok") -> ok | E3: =IFERROR(IF(ABS(E101)>1,"ERROR","ok"),"ok") -> ok | F3: =IFERROR(IF(ABS(F101)>1,"ERROR","ok"),"ok") -> ok | G3: =IFERROR(IF(ABS(G101)>1,"ERROR","ok"),"ok") -> ok | H3: =IFERROR(IF(ABS(H101)>1,"ERROR","ok"),"ok") -> ok | I3: =IFERROR(IF(ABS(I101)>1,"ERROR","ok"),"ok") -> ok | J3: =IFERROR(IF(ABS(J101)>1,"ERROR","ok"),"ok") -> ok | K3: =IFERROR(IF(ABS(K101)>1,"ERROR","ok"),"ok") -> ok | ... N3: =IFERROR(IF(ABS(N101)>1,"ERROR","ok"),"ok") -> ok
A4: End of Period | D4: 41274 | E4: =EOMONTH(D4,12) -> 41639 | F4: =EOMONTH(E4,12) -> 42004 | G4: =EOMONTH(F4,12) -> 42369 | H4: =EOMONTH(G4,12) -> 42735 | I4: =EOMONTH(H4,12) -> 43100 | J4: =EOMONTH(I4,12) -> 43465 | K4: =EOMONTH(J4,12) -> 43830 | L4: =EOMONTH(K4,12) -> 44196 | ... N4: =EOMONTH(M4,12) -> 44926 | O4: =+'M&A Assumptions & Analysis'!D10 -> 45838 | P4: =+EOMONTH(O4,P6*12) -> 46203
A5: Days in Period | D5: 366 | E5: =E4-D4 -> 365 | F5: =F4-E4 -> 365 | G5: =G4-F4 -> 365 | H5: =H4-G4 -> 366 | I5: =I4-H4 -> 365 | J5: =J4-I4 -> 365 | K5: =K4-J4 -> 365 | L5: =L4-K4 -> 366 | ... N5: =N4-M4 -> 365 | O5: 365 | P5: 365
A6: Fraction of Year | D6: 1 | E6: =D6 -> 1 | F6: =E6 -> 1 | G6: =F6 -> 1 | H6: =G6 -> 1 | I6: =H6 -> 1 | J6: =I6 -> 1 | K6: =J6 -> 1 | L6: =K6 -> 1 | ... N6: =M6 -> 1 | O6: 1 | P6: 1
A8: Assumptions
H10: LIVE SCENARIO | I10: 1
A12: SCENARIO 1
A13: Revenue Growth (% Change) | I13: 0.15 | J13: 0.15 | K13: 0.12 | L13: 0.1 | M13: 0.08 | N13: 0.06 | O13: 0.15 | P13: 0.15
A14: Cost of Goods Sold (% of Revenue) | I14: 0.42 | J14: 0.41 | K14: 0.4 | L14: 0.4 | M14: 0.4 | N14: 0.4 | O14: 0.42 | P14: 0.42
A15: Salaries and Benefits (% of Revenue) | I15: 0.16 | J15: 0.16 | K15: 0.16 | L15: 0.16 | M15: 0.16 | N15: 0.16 | O15: 0.16 | P15: 0.16
A16: Rent and Overhead ($000's) | I16: 7000 | J16: 7000 | K16: 7000 | L16: 7000 | M16: 7000 | N16: 7000 | O16: 7000 | P16: 7000
A17: Depreciation & Amortization (% of PP&E) | I17: 0.2 | J17: 0.2 | K17: 0.2 | L17: 0.2 | M17: 0.2 | N17: 0.2 | O17: 0.2 | P17: 0.2
A18: Interest (% of Debt) | I18: 0.08 | J18: 0.08 | K18: 0.08 | L18: 0.08 | M18: 0.08 | N18: 0.08 | O18: 0.08 | P18: 0.08
A19: Tax Rate (% of Earnings Before Tax) | I19: 0.32 | J19: 0.32 | K19: 0.32 | L19: 0.32 | M19: 0.32 | N19: 0.32 | O19: 0.32 | P19: 0.32
A20: Accounts Receivable (Days) | I20: 22 | J20: 18 | K20: 18 | L20: 18 | M20: 18 | N20: 18 | O20: 22 | P20: 22
A21: Inventory (Days) | I21: 75 | J21: 75 | K21: 75 | L21: 75 | M21: 75 | N21: 75 | O21: 75 | P21: 75
A22: Accounts Payable (Days) | I22: 39 | J22: 39 | K22: 39 | L22: 39 | M22: 39 | N22: 39 | O22: 39 | P22: 39
A23: Capital Expenditures ($000's) | I23: 5750 | J23: 5750 | K23: 5750 | L23: 5750 | M23: 5750 | N23: 5750 | O23: 5750 | P23: 5750
A24: Debt Issuance (Repayment) ($000's) | I24: 0 | J24: 0 | K24: 0 | L24: 0 | M24: 0 | N24: -10000 | O24: 0 | P24: 0
... A26: Payment of Dividends | I26: 0 | J26: 0 | K26: 0 | L26: 0 | M26: 200 | N26: 200 | O26: 0 | P26: 0
A28: SCENARIO 2
A29: Revenue Growth (% Change) | I29: 0.05 | J29: 0.045 | K29: 0.04 | L29: 0.035 | M29: 0.03 | N29: 0.03 | O29: 0.05 | P29: 0.05
A30: Cost of Goods Sold (% of Revenue) | I30: 0.37 | J30: 0.37 | K30: 0.36 | L30: 0.36 | M30: 0.35 | N30: 0.35 | O30: 0.37 | P30: 0.37
A31: Salaries and Benefits (% of Revenue) | I31: 0.17 | J31: 0.17 | K31: 0.17 | L31: 0.17 | M31: 0.17 | N31: 0.17 | O31: 0.17 | P31: 0.17
A32: Rent and Overhead ($000's) | I32: 10000 | J32: 10000 | K32: 10000 | L32: 10000 | M32: 10000 | N32: 10000 | O32: 10000 | P32: 10000
A33: Depreciation & Amortization (% of PP&E) | I33: 0.2 | J33: 0.2 | K33: 0.2 | L33: 0.2 | M33: 0.2 | N33: 0.2 | O33: 0.2 | P33: 0.2
A34: Interest (% of Debt) | I34: 0.05 | J34: 0.05 | K34: 0.05 | L34: 0.05 | M34: 0.05 | N34: 0.05 | O34: 0.05 | P34: 0.05
A35: Tax Rate (% of Earnings Before Tax) | I35: 0.28 | J35: 0.28 | K35: 0.28 | L35: 0.28 | M35: 0.28 | N35: 0.28 | O35: 0.28 | P35: 0.28
A36: Accounts Receivable (Days) | I36: 18 | J36: 18 | K36: 18 | L36: 18 | M36: 18 | N36: 18 | O36: 18 | P36: 18
A37: Inventory (Days) | I37: 73 | J37: 73 | K37: 73 | L37: 73 | M37: 73 | N37: 73 | O37: 73 | P37: 73
A38: Accounts Payable (Days) | I38: 37 | J38: 37 | K38: 37 | L38: 37 | M38: 37 | N38: 37 | O38: 37 | P38: 37
A39: Capital Expenditures ($000's) | I39: 15000 | J39: 15000 | K39: 15000 | L39: 15000 | M39: 15000 | N39: 15000 | O39: 15000 | P39: 15000
A40: Debt Issuance (Repayment) ($000's) | I40: 0 | J40: 0 | K40: -20000 | L40: 0 | M40: 0 | N40: 0 | O40: 0 | P40: 0
... A42: Payment of Dividends | I42: 0 | J42: 0 | K42: 0 | L42: 0 | M42: 100 | N42: 100 | O42: 0 | P42: 0
A44: LIVE SCENARIO
A45: Revenue Growth (% Change) | I45: 0.15 | J45: 0.15 | K45: 0.12 | L45: 0.1 | M45: 0.08 | N45: 0.06 | O45: 0.15 | P45: 0.15
A46: Cost of Goods Sold (% of Revenue) | I46: 0.42 | J46: 0.41 | K46: 0.4 | L46: 0.4 | M46: 0.4 | N46: 0.4 | O46: 0.42 | P46: 0.42
A47: Marketing, Advertising & Promotion (% of Revenue) | I47: 0.16 | J47: 0.16 | K47: 0.16 | L47: 0.16 | M47: 0.16 | N47: 0.16 | O47: 0.16 | P47: 0.16
A48: General & Administrative ($000's) | I48: 7000 | J48: 7000 | K48: 7000 | L48: 7000 | M48: 7000 | N48: 7000 | O48: 7000 | P48: 7000
A49: Depreciation & Amortization (% of PP&E) | I49: 0.2 | J49: 0.2 | K49: 0.2 | L49: 0.2 | M49: 0.2 | N49: 0.2 | O49: 0.2 | P49: 0.2
A50: Interest (% of Debt) | I50: 0.08 | J50: 0.08 | K50: 0.08 | L50: 0.08 | M50: 0.08 | N50: 0.08 | O50: 0.08 | P50: 0.08
A51: Tax Rate (% of Earnings Before Tax) | I51: 0.32 | J51: 0.32 | K51: 0.32 | L51: 0.32 | M51: 0.32 | N51: 0.32 | O51: 0.32 | P51: 0.32
A52: Accounts Receivable (Days) | I52: 22 | J52: 18 | K52: 18 | L52: 18 | M52: 18 | N52: 18 | O52: 22 | P52: 22
A53: Inventory (Days) | I53: 75 | J53: 75 | K53: 75 | L53: 75 | M53: 75 | N53: 75 | O53: 75 | P53: 75
A54: Accounts Payable (Days) | I54: 39 | J54: 39 | K54: 39 | L54: 39 | M54: 39 | N54: 39 | O54: 39 | P54: 39
A55: Capital Expenditures ($000's) | I55: 5750 | J55: 5750 | K55: 5750 | L55: 5750 | M55: 5750 | N55: 5750 | O55: 5750 | P55: 5750
A56: Debt Issuance (Repayment) ($000's) | I56: 0 | J56: 0 | K56: 0 | L56: 0 | M56: 0 | N56: -10000 | O56: 0 | P56: 0
... A58: Payment of Dividends | I58: 0 | J58: 0 | K58: 0 | L58: 0 | M58: 200 | N58: 200 | O58: 0 | P58: 0
A61: Income Statement
A63: Revenue | D63: 57127.576 | E63: 66132.392 | F63: 73557.908 | G63: 79716.062 | H63: 84437.724 | I63: =H63*1.15 -> 97103.383 | J63: =I63*1.15 -> 111668.89 | K63: =J63*1.12 -> 125069.16 | L63: =K63*1.1 -> 137576.07 | M63: =L63*1.08 -> 148582.16 | N63: =M63*1.06 -> 157497.09 | O63: =N63*1.15 -> 181121.65 | P63: =O63*1.15 -> 208289.9
A64: Cost of Goods Sold (COGS) | D64: 21854.279 | E64: 26883.961 | F64: 27510.641 | G64: 29488.127 | H64: 31759.633 | I64: =I63*(I46) -> 40783.421 | J64: =J63*(J46) -> 45784.245 | K64: =K63*(K46) -> 50027.663 | L64: =L63*(L46) -> 55030.429 | M64: =M63*(M46) -> 59432.863 | N64: =N63*(N46) -> 62998.835 | O64: =O63*O46 -> 76071.093 | P64: =P63*P46 -> 87481.757
A65: Gross Profit | D65: =D63-D64 -> 35273.297 | E65: =E63-E64 -> 39248.432 | F65: =F63-F64 -> 46047.267 | G65: =G63-G64 -> 50227.935 | H65: =H63-H64 -> 52678.091 | I65: =I63-I64 -> 56319.962 | J65: =J63-J64 -> 65884.645 | K65: =K63-K64 -> 75041.494 | ... P65: =P63-P64 -> 120808.14
A66: Expenses
A67: Marketing, Advertising & Promotion | D67: 14800.067 | E67: 12689.292 | F67: 13369.176 | G67: 12881.944 | H67: 14138.105 | I67: =I63*I47 -> 15536.541 | J67: =J63*J47 -> 17867.022 | K67: =K63*K47 -> 20011.065 | L67: =L63*L47 -> 22012.172 | M67: =M63*M47 -> 23773.145 | N67: =N63*N47 -> 25199.534 | O67: =O63*O47 -> 28979.464 | P67: =P63*P47 -> 33326.384
A68: General & Administrative | D68: 6139.6729 | E68: 5670.3629 | F68: 5649.0815 | G68: 6171.595 | H68: 6391.129 | I68: =I48 -> 7000 | J68: =J48 -> 7000 | K68: =K48 -> 7000 | L68: =L48 -> 7000 | M68: =M48 -> 7000 | N68: =N48 -> 7000 | O68: =O48 -> 7000 | P68: =P48 -> 7000
A69: Depreciation & Amortization | D69: 10920.699 | E69: 10164.651 | F69: 9635.4167 | G69: 9264.953 | H69: 9005.6284 | I69: 4202.6266 | J69: 4512.1013 | K69: 4759.681 | L69: 4957.7448 | M69: 5116.1958 | N69: 5242.9567 | O69: 5344.4 | P69: 5426
A70: Interest | D70: 1400.0896 | E70: 1400.0896 | F70: 840.05376 | G70: 840.05376 | H70: 840.05376 | I70: 1344.086 | J70: 1344.086 | K70: 1344.086 | L70: 1344.086 | M70: 1344.086 | N70: 544.08602 | O70: 544.08 | P70: 544.08
A71: Total Expenses | D71: =SUM(D67:D70) -> 33260.529 | E71: =SUM(E67:E70) -> 29924.395 | F71: =SUM(F67:F70) -> 29493.728 | G71: =SUM(G67:G70) -> 29158.546 | H71: =SUM(H67:H70) -> 30374.916 | I71: =SUM(I67:I70) -> 28083.254 | J71: =SUM(J67:J70) -> 30723.21 | K71: =SUM(K67:K70) -> 33114.832 | ... P71: =SUM(P67:P70) -> 46296.464
A72: Earnings Before Tax | D72: =D65-D71 -> 2012.7688 | E72: =E65-E71 -> 9324.0367 | F72: =F65-F71 -> 16553.539 | G72: =G65-G71 -> 21069.388 | H72: =H65-H71 -> 22303.175 | I72: =I65-I71 -> 28236.708 | J72: =J65-J71 -> 35161.435 | K72: =K65-K71 -> 41926.662 | ... P72: =P65-P71 -> 74511.677
A74: Taxes | D74: 1120.1708 | E74: 4858.2165 | F74: 8482.8061 | G74: 10908.021 | H74: 11597.665 | I74: =I72*I51 -> 9035.7466 | J74: =J72*J51 -> 11251.659 | K74: =K72*K51 -> 13416.532 | L74: =L72*L51 -> 15114.125 | M74: =M72*M51 -> 16613.078 | N74: =N72*N51 -> 18083.736 | O74: =O72*O51 -> 20218.436 | P74: =P72*P51 -> 23843.737
A75: Net Earnings | D75: =D72-D74 -> 892.59802 | E75: =E72-E74 -> 4465.8202 | F75: =F72-F74 -> 8070.7333 | G75: =G72-G74 -> 10161.367 | H75: =H72-H74 -> 10705.51 | I75: =I72-I74 -> 19200.962 | J75: =J72-J74 -> 23909.776 | K75: =K72-K74 -> 28510.13 | ... P75: =P72-P74 -> 50667.941
A78: Balance Sheet
A80: Assets
A81: Cash | D81: 37573.462 | E81: 42850.186 | F81: 40521.137 | G81: 51041.264 | H81: 61888.631 | I81: 77064.788 | J81: 99588.665 | K81: 126029.11 | L81: 156244.17 | M81: 189736.18 | N81: 216665.72 | O81: 254785.32 | P81: 302365.8
A82: Accounts Receivable | D82: 2856.3788 | E82: 3306.6196 | F82: 3677.8954 | G82: 3985.8031 | H82: 4221.8862 | I82: =I63*I52/365 -> 5852.8066 | J82: =J63*J52/365 -> 5506.959 | K82: =K63*K52/365 -> 6167.794 | L82: =L63*L52/365 -> 6784.5734 | M82: =M63*M52/365 -> 7327.3393 | N82: =N63*N52/365 -> 7766.9797 | O82: =O63*O52/365 -> 10916.921 | P82: =P63*P52/365 -> 12554.46
A83: Inventory | D83: 4370.8557 | E83: 5376.7921 | F83: 5502.1281 | G83: 5897.6254 | H83: 6351.9265 | I83: =I64*I53/365 -> 8380.1549 | J83: =J64*J53/365 -> 9407.7216 | K83: =K64*K53/365 -> 10279.657 | L83: =L64*L53/365 -> 11307.622 | M83: =M64*M53/365 -> 12212.232 | N83: =N64*N53/365 -> 12944.966 | O83: =O64*O53/365 -> 15631.047 | P83: =P64*P53/365 -> 17975.704
A84: Current Assets | D84: =SUM(D81:D83) -> 44800.696 | E84: =SUM(E81:E83) -> 51533.597 | F84: =SUM(F81:F83) -> 49701.161 | G84: =SUM(G81:G83) -> 60924.692 | H84: =SUM(H81:H83) -> 72462.444 | I84: =SUM(I81:I83) -> 91297.749 | J84: =SUM(J81:J83) -> 114503.35 | K84: =SUM(K81:K83) -> 142476.56 | L84: 174337 | M84: =SUM(M81:M83) -> 209275.75 | N84: =SUM(N81:N83) -> 237377.67 | O84: =SUM(O81:O83) -> 281333.28 | P84: =SUM(P81:P83) -> 332895.97
A85: Property & Equipment | D85: 25481.631 | E85: 23717.518 | F85: 22482.639 | G85: 21618.224 | H85: 21013.133 | I85: 22560.506 | J85: 23798.405 | K85: 24788.724 | L85: 25580.979 | M85: 26214.783 | N85: 26721.827 | O85: 27127.6 | P85: 27452.08
A86: Goodwill
A87: Total Assets | D87: =SUM(D84:D86) -> 70282.327 | E87: =SUM(E84:E86) -> 75251.115 | F87: =SUM(F84:F86) -> 72183.8 | G87: =SUM(G84:G86) -> 82542.916 | H87: =SUM(H84:H86) -> 93475.577 | I87: =SUM(I84:I86) -> 113858.26 | J87: =SUM(J84:J86) -> 138301.75 | K87: 167266 | L87: =SUM(L84:L86) -> 199917.98 | M87: =SUM(M84:M86) -> 235490.53 | N87: 264100 | O87: =SUM(O84:O86) -> 308460.88 | P87: =SUM(P84:P86) -> 360348.05
A89: Liabilities
A90: Short Term Debt | D90: 0 | E90: 0 | F90: 0 | G90: 0 | H90: 0 | I90: - | J90: - | K90: - | L90: - | M90: - | N90: - | O90: - | P90: -
A91: Accounts Payable | D91: 2185.4279 | E91: 2688.3961 | F91: 2751.0641 | G91: 2948.8127 | H91: 3175.9633 | I91: =I64*I54/365 -> 4357.6806 | J91: =J64*J54/365 -> 4892.0152 | K91: =K64*K54/365 -> 5345.4215 | L91: =L64*L54/365 -> 5879.9636 | M91: =M64*M54/365 -> 6350.3607 | N91: =N64*N54/365 -> 6731.3824 | O91: =O64*O54/365 -> 8128.1442 | P91: =P64*P54/365 -> 9347.3659
A92: Current Liabilities | D92: =SUM(D90:D91) -> 2185.4279 | E92: =SUM(E90:E91) -> 2688.3961 | F92: =SUM(F90:F91) -> 2751.0641 | G92: =SUM(G90:G91) -> 2948.8127 | H92: =SUM(H90:H91) -> 3175.9633 | I92: =SUM(I90:I91) -> 4357.6806 | J92: =SUM(J90:J91) -> 4892.0152 | K92: =SUM(K90:K91) -> 5345.4215 | ... P92: =SUM(P90:P91) -> 9347.3659
A93: Long Term Debt | D93: 28001.792 | E93: 28001.792 | F93: 16801.075 | G93: 16801.075 | H93: 16801.075 | I93: 16801.075 | J93: 16801.075 | K93: 16801.075 | L93: 16801.075 | M93: 16801.075 | N93: 6801.0753 | O93: 6801 | P93: 6801
A94: Total Liabilities | D94: =SUM(D92:D93) -> 30187.22 | E94: =SUM(E92:E93) -> 30690.188 | F94: =SUM(F92:F93) -> 19552.139 | G94: =SUM(G92:G93) -> 19749.888 | H94: =SUM(H92:H93) -> 19977.039 | I94: =SUM(I92:I93) -> 21158.756 | J94: =SUM(J92:J93) -> 21693.09 | K94: =SUM(K92:K93) -> 22146.497 | ... P94: =SUM(P92:P93) -> 16148.366
A95: Shareholder's Equity
A96: Equity Capital | D96: 39202.509 | E96: 39202.509 | F96: 39202.509 | G96: 39202.509 | H96: 39202.509 | I96: =H96+I57 -> 39202.509 | J96: =I96+J57 -> 39202.509 | K96: =J96+K57 -> 39202.509 | L96: =K96+L57 -> 39202.509 | M96: =L96+M57 -> 39202.509 | N96: =M96+N57 -> 39202.509 | O96: =H96+O57 -> 39202.509 | P96: =+I96 -> 39202.509
A97: Retained Earnings | D97: 892.59802 | E97: 5358.4183 | F97: 13429.152 | G97: 23590.519 | H97: 34296.029 | I97: =H97+I75-I58 -> 53496.991 | J97: =I97+J75-J58 -> 77406.767 | K97: =J97+K75-K58 -> 105916.9 | L97: =K97+L75-L58 -> 138034.41 | M97: =L97+M75-M58 -> 173137.2 | N97: =M97+N75-N58 -> 211365.14 | O97: =N97+O75-O58 -> 254329.32 | P97: =O97+P75-P58 -> 304997.26
A98: Shareholder's Equity | D98: =SUM(D96:D97) -> 40095.107 | E98: =SUM(E96:E97) -> 44560.927 | F98: =SUM(F96:F97) -> 52631.661 | G98: =SUM(G96:G97) -> 62793.028 | H98: =SUM(H96:H97) -> 73498.538 | I98: =SUM(I96:I97) -> 92699.5 | J98: =SUM(J96:J97) -> 116609.28 | K98: =SUM(K96:K97) -> 145119.41 | ... P98: =SUM(P96:P97) -> 344199.77
A99: Total Liabilities & Shareholder's Equity | D99: =D94+D98 -> 70282.327 | E99: =E94+E98 -> 75251.115 | F99: =F94+F98 -> 72183.8 | G99: =G94+G98 -> 82542.916 | H99: =H94+H98 -> 93475.577 | I99: =I98+I94 -> 113858.26 | J99: =J98+J94 -> 138302.37 | K99: =K98+K94 -> 167265.9 | L99: =L98+L94 -> 199917.96 | M99: =M98+M94 -> 235491.15 | N99: =N98+N94 -> 264100.11 | O99: =O98+O94 -> 308460.97 | P99: =P98+P94 -> 360348.14
A101: Check | D101: =D99-D87 -> 0 | E101: =E99-E87 -> 0 | F101: =F99-F87 -> 0 | G101: =G99-G87 -> 0 | H101: =H99-H87 -> 0 | I101: =I99-I87 -> 0 | J101: =J99-J87 -> 0.61568775 | K101: =K99-K87 -> -0.097336933 | ... P101: =P99-P87 -> 0.088143695
A104: Cash Flow Statement
A106: Operating Cash Flow
A107: Net Earnings | D107: =D75 -> 892.59802 | E107: =E75 -> 4465.8202 | F107: =F75 -> 8070.7333 | G107: =G75 -> 10161.367 | H107: =H75 -> 10705.51 | I107: =I75 -> 19200.962 | J107: =J75 -> 23909.776 | K107: =K75 -> 28510.13 | ... P107: =P75 -> 50667.941
A108: Plus: Depreciation & Amortization | D108: =D69 -> 10920.699 | E108: =E69 -> 10164.651 | F108: =F69 -> 9635.4167 | G108: =G69 -> 9264.953 | H108: =H69 -> 9005.6284 | I108: 4202.6266 | J108: 4512.1013 | K108: 4759.681 | L108: 4957.7448 | M108: 5116.1958 | N108: 5242.9567 | O108: 5344.4 | P108: 5425.52
A109: Less: Changes in Working Capital | D109: 5041.8067 | E109: 953.20901 | F109: 433.94377 | G109: 505.65636 | H109: 463.23365 | I109: 2477.4315 | J109: 148 | K109: 1079.364 | L109: 1110.2029 | M109: 976.97858 | N109: 791.35265 | O109: 4439.2604 | P109: 2762.9736
A110: Cash from Operations | D110: =D107+D108-D109 -> 6771.4903 | E110: =E107+E108-E109 -> 13677.262 | F110: =F107+F108-F109 -> 17272.206 | G110: =G107+G108-G109 -> 18920.664 | H110: =H107+H108-H109 -> 19247.905 | I110: =I107+I108-I109 -> 20926.157 | J110: =J107+J108-J109 -> 28273.877 | K110: =K107+K108-K109 -> 32190.447 | ... P110: =P107+P108-P109 -> 53330.487
A112: Investing Cash Flow
A113: Investments in Property & Equipment | D113: -8400.5376 | E113: -8400.5376 | F113: -8400.5376 | G113: -8400.5376 | H113: -8400.5376 | I113: =-I140 -> -5750 | J113: =-J140 -> -5750 | K113: =-K140 -> -5750 | L113: =-L140 -> -5750 | M113: =-M140 -> -5750 | N113: =-N140 -> -5750 | O113: =-O140 -> -5750 | P113: =-P140 -> -5750
A114: Investments in Businesses
A115: Cash from Investing | D115: =SUM(D113:D114) -> -8400.5376 | E115: =SUM(E113:E114) -> -8400.5376 | F115: =SUM(F113:F114) -> -8400.5376 | G115: =SUM(G113:G114) -> -8400.5376 | H115: =SUM(H113:H114) -> -8400.5376 | I115: =SUM(I113:I114) -> -5750 | J115: =SUM(J113:J114) -> -5750 | K115: =SUM(K113:K114) -> -5750 | ... P115: =SUM(P113:P114) -> -5750
A117: Financing Cash Flow
A118: Issuance (repayment) of debt | D118: 0 | E118: 0 | F118: -11200.717 | G118: 0 | H118: 0 | I118: =I146 -> 0 | J118: =J146 -> 0 | K118: =K146 -> 0 | L118: =L146 -> 0 | M118: =M146 -> 0 | N118: =N146 -> -10000 | O118: =O146 -> 0 | P118: =P146 -> 0
A119: Issuance (repayment) of equity | D119: 39202.509 | E119: 0 | F119: 0 | G119: 0 | H119: 0 | I119: =I57 -> 0 | J119: =J57 -> 0 | K119: =K57 -> 0 | L119: =L57 -> 0 | M119: =M57 -> 0 | N119: =N57 -> 0 | O119: =O57 -> 0 | P119: =P57 -> 0
A120: Payment of Dividends | D120: 0 | E120: 0 | F120: 0 | G120: 0 | H120: 0 | I120: =-I58 -> 0 | J120: =-J58 -> 0 | K120: =-K58 -> 0 | L120: =-L58 -> 0 | M120: =-M58 -> -200 | N120: =-N58 -> -200 | O120: =-O58 -> 0 | P120: =-P58 -> 0
A121: Cash from Financing | D121: =SUM(D118:D120) -> 39202.509 | E121: =SUM(E118:E120) -> 0 | F121: =SUM(F118:F120) -> -11200.717 | G121: =SUM(G118:G120) -> 0 | H121: =SUM(H118:H120) -> 0 | I121: =SUM(I118:I120) -> 0 | J121: =SUM(J118:J120) -> 0 | K121: =SUM(K118:K120) -> 0 | ... P121: =SUM(P118:P120) -> 0
A123: Net Increase (decrease) in Cash | D123: =D110+D115+D121 -> 37573.462 | E123: =E110+E115+E121 -> 5276.7241 | F123: =F110+F115+F121 -> -2329.0483 | G123: =G110+G115+G121 -> 10520.126 | H123: =H110+H115+H121 -> 10847.367 | I123: =I110+I115+I121 -> 15176.157 | J123: =J110+J115+J121 -> 22523.877 | K123: =K110+K115+K121 -> 26440.447 | ... P123: =P110+P115+P121 -> 47580.487
...
